Workbook

Sheet Estimate
A1: Eun/Yu Residence -- 28 Country Club Lane South
A2: 28 Country Club Lane South, Briarcliff Manor, NY 10510 | Internal Estimate Report (Scope / Leveling)
A3: Date: 2026-09-23 | C3: Prepared By: BLDG Estimating | Job E26040 | Client: Resolution: 4 Architecture / Eun-Yu
A5: F/I = Furnish and Install | F/O = Furnish Only | I/O = Install Only | Remove = Demolition | Provide = Services | LS = Lump Sum | Alternates begin at row 501
A6: GREEN = concrete priced from the drawing takeoff (CY at adjusted $/CY). BLUE = NOVATerra takeoff matched to SOW scope (INCL = covered by the priced line above it). AMBER = priced takeoff item with no SOW match, added. Unshaded = SOW scope not priced in takeoff. Sub bids: enter a lump sum on the trade header row or price line by line. LAVENDER = electrical / shade pricing added 2026-09-28 (conceptual unit pricing; hover column B for furnish/install split and basis).
A8: CSI | B8: Scope Item | C8: Qty | D8: Unit | E8: Unit Rate | F8: Total | H8: Sub #1 | I8: Sub #2 | J8: Sub #3 | K8: Sub #4
A9: DEMOLITION | H9: Luigi | I9: Sub #2 | J9: Sub #3 | K9: Sub #4
F11: =IF(AND(ISNUMBER($C11),ISNUMBER($E11)),$C11*$E11,"")
F12: =IF(AND(ISNUMBER($C12),ISNUMBER($E12)),$C12*$E12,"")
F13: =IF(AND(ISNUMBER($C13),ISNUMBER($E13)),$C13*$E13,"")
F14: =IF(AND(ISNUMBER($C14),ISNUMBER($E14)),$C14*$E14,"")
F15: =IF(AND(ISNUMBER($C15),ISNUMBER($E15)),$C15*$E15,"")
F16: =IF(AND(ISNUMBER($C16),ISNUMBER($E16)),$C16*$E16,"")
A17: TRADE TOTAL | F17: =IF(SUM(F11:F16)=0,"-",SUM(F11:F16)) -> - | H17: =IF(SUM(H10:H16)=0,"-",SUM(H10:H16)) -> - | I17: =IF(SUM(I10:I16)=0,"-",SUM(I10:I16)) -> - | J17: =IF(SUM(J10:J16)=0,"-",SUM(J10:J16)) -> - | K17: =IF(SUM(K10:K16)=0,"-",SUM(K10:K16)) -> -
A19: CONCRETE | H19: Sub #1 | I19: Sub #2 | J19: Sub #3 | K19: Sub #4
A21: 03.30.00 | B21: F/I Reinforced Concrete Foundation Walls And Footings At House Basement [REINFORCED CONC. FOUNDATION WALL & FOOTING AS PER STR. ENG. DWGS] (Foundation) -- Ref: 02/A1.10, S-RL A1.10, SUPP Sec. 6.3 | C21: 81.9564 | D21: CY | E21: 640 | F21: =IF(AND(ISNUMBER($C21),ISNUMBER($E21)),$C21*$E21,"") -> 52452.096
A22: 03.30.00 | B22: F/I Spread Footings Bearing On Virgin Soil Or New Structural Fill [NET DESIGN BEARING PRESSURE 4,000 PSF; MINIMUM FROST DEPTH 42 INCHES] (Foundation) -- Ref: GEO Table 2 | D22: INCL | F22: =IF(AND(ISNUMBER($C22),ISNUMBER($E22)),$C22*$E22,"")
A23: 03.30.00 | B23: F/I 4" SEALED REINFORCED CONCRETE SLAB PER STRUCT. & STEGO WRAP 15-MIL VAPOR BARRIER PER STRUCT.] (Foundation) -- Ref: 04/A0.24, 02/A1.10 | C23: 16.0909 | D23: CY | E23: 690.00111 | F23: =IF(AND(ISNUMBER($C23),ISNUMBER($E23)),$C23*$E23,"") -> 11102.739
A24: 03.30.00 | B24: Provide Smooth Troweled Finish At Basement Slab [CONC. SLAB W SMOOTH TROWELED FINISH IN PHASE 1.] (Foundation) -- Ref: A1.40 | D24: INCL | F24: =IF(AND(ISNUMBER($C24),ISNUMBER($E24)),$C24*$E24,"")
A25: 03.30.00 | B25: F/I Recessed Threshold Formed Into Concrete Foundation Wall And Formed Concrete Ledge At Sliding Door #003 [FORMED CONC. LEDGE PER STRUCT. TO SUPPORT MASONRY SILL ABOVE] (Foundation) -- Ref: 04/A0.24 | D25: INCL | F25: =IF(AND(ISNUMBER($C25),ISNUMBER($E25)),$C25*$E25,"")
A26: 03.30.00 | B26: F/I Concrete Pile Caps At Rear Deck [9'x9' PILE CAP W/ (4) PILES] (Decks) -- Ref: S-RL A1.10 | C26: 18.9 | D26: CY | E26: 750 | F26: =IF(AND(ISNUMBER($C26),ISNUMBER($E26)),$C26*$E26,"") -> 14175
A27: 03.30.00 | B27: F/I Garage Foundation Walls, Frost Walls And Footings [PER STR. ENG. DWGS] (Garage) -- Ref: 02/A1.10, S-RL A1.10, 01/A3.00 | C27: 32.8928 | D27: CY | E27: 650 | F27: =IF(AND(ISNUMBER($C27),ISNUMBER($E27)),$C27*$E27,"") -> 21380.32
A28: 03.30.00 | B28: F/I Garage And Garage Storage Slab On Grade With Smooth Troweled Finish [CONC. SLAB W SMOOTH TROWELED FINISH] (Garage) -- Ref: A1.41, A2.10 | C28: 10.6556 | D28: CY | E28: 600 | F28: =IF(AND(ISNUMBER($C28),ISNUMBER($E28)),$C28*$E28,"") -> 6393.36
A29: 03.30.00 | B29: F/I Terrace Slab On Grade And Concrete Piers / Footings At Outdoor Living, Dining And Kitchen [SLAB ON GRADE] (Foundation) -- Ref: S-RL A1.11, 01/A2.10, SUPP Sec. 5 | C29: 31.2072 | D29: CY | E29: 650 | F29: =IF(AND(ISNUMBER($C29),ISNUMBER($E29)),$C29*$E29,"") -> 20284.68
A30: 03.30.00 | B30: Set Anchor Bolts For 2X8 Double Sill Plates On Foundation Walls [ANCHOR BOLTS PER STR. ENG. DWGS] (Foundation) -- Ref: A1.10 Gen. Note 01, 02/A1.10 | D30: INCL | F30: =IF(AND(ISNUMBER($C30),ISNUMBER($E30)),$C30*$E30,"")
A31: 03.30.00 | B31: F/I Footings And Base Plate Anchorage For Structural Steel Posts [Not Specified] (Foundation) -- Ref: S-RL A1.11, S-RL A1.12 | D31: INCL | F31: =IF(AND(ISNUMBER($C31),ISNUMBER($E31)),$C31*$E31,"")
A32: 03.40.00 | B32: F/I Precast Concrete Sill Sloped To Drain On Mortar Bed With Weeps At Sliding Door #003 [PRECAST CONC. SILL, SLOPED TO DRAIN] (Foundation) -- Ref: 02/A0.24, 04/A0.24 | C32: 15.83 | D32: LF | E32: 150 | F32: =IF(AND(ISNUMBER($C32),ISNUMBER($E32)),$C32*$E32,"") -> 2374.5
B33: Concrete Testingt | C33: 1 | D33: LS | E33: 3500 | F33: =IF(AND(ISNUMBER($C33),ISNUMBER($E33)),$C33*$E33,"") -> 3500
A34: TRADE TOTAL | F34: =IF(SUM(F21:F33)=0,"-",SUM(F21:F33)) -> 131662.69 | H34: =IF(SUM(H20:H33)=0,"-",SUM(H20:H33)) -> - | I34: =IF(SUM(I20:I33)=0,"-",SUM(I20:I33)) -> - | J34: =IF(SUM(J20:J33)=0,"-",SUM(J20:J33)) -> - | K34: =IF(SUM(K20:K33)=0,"-",SUM(K20:K33)) -> -
A36: STRUCTURAL STEEL | H36: Paulie D | I36: Sub #2 | J36: Sub #3 | K36: Sub #4
H37: 330000
A38: 05.12.00 | B38: F/I Structural Steel Beams At First Floor Deck And Module D [W10x26; W12x65; W16x89] (Decks) -- Ref: S-RL A1.11, SUPP Sec. 6.5 | C38: 12552.05 | D38: LB | E38: 5 | F38: =IF(AND(ISNUMBER($C38),ISNUMBER($E38)),$C38*$E38,"") -> 62760.25
A39: 05.12.00 | B39: F/I Structural Steel Beams At Module Bearing Lines [W14X38; W14X68] (House) -- Ref: S-RL A1.11 | C39: 5945.88 | D39: LB | E39: 5 | F39: =IF(AND(ISNUMBER($C39),ISNUMBER($E39)),$C39*$E39,"") -> 29729.4
A40: 05.12.00 | B40: F/I Structural Steel Beams At Second Floor Overhang / Module E And F Support [W10X26; W10X22; W16X67; W16X89] (House) -- Ref: S-RL A1.12 | C40: 12066.03 | D40: LB | E40: 5 | F40: =IF(AND(ISNUMBER($C40),ISNUMBER($E40)),$C40*$E40,"") -> 60330.15
A41: 05.12.00 | B41: F/I Steel Tube Beams At Garage Roof Edge [HSS 9x5x1/4"] (Garage) -- Ref: S-RL A1.12 | C41: 518.13 | D41: LB | E41: 5 | F41: =IF(AND(ISNUMBER($C41),ISNUMBER($E41)),$C41*$E41,"") -> 2590.65
A42: 05.12.00 | B42: Provide Moment Connections Where Indicated [MOMENT CONNECTION] (House) -- Ref: S-RL A1.11, S-RL A1.12, S-RL A1.13 | D42: INCL | F42: =IF(AND(ISNUMBER($C42),ISNUMBER($E42)),$C42*$E42,"")
A43: 05.12.00 | B43: F/I P1 Structural Posts Supporting Second Floor Modules At Terrace [P1 - HSS 12x4x1/2"] (House) -- Ref: S-RL A1.11, A1.11 Keynote 1 | C43: 13189.5 | D43: EA | E43: 5 | F43: =IF(AND(ISNUMBER($C43),ISNUMBER($E43)),$C43*$E43,"") -> 65947.5
A44: 05.12.00 | B44: F/I P2 Structural Posts Supporting Deck / Overhang [P2 - (2) 2x6 STL. PLATE] (Decks) -- Ref: S-RL A1.11, A1.10 Keynote 4 | C44: 9792 | D44: EA | E44: 5 | F44: =IF(AND(ISNUMBER($C44),ISNUMBER($E44)),$C44*$E44,"") -> 48960
A45: 05.12.00 | B45: F/I P3 Posts At Front Stair Glazing [P3 - HSS 6x6x1/2"] (House) -- Ref: S-RL A1.11, S-RL A1.12 | C45: 3524 | D45: EA | E45: 5 | F45: =IF(AND(ISNUMBER($C45),ISNUMBER($E45)),$C45*$E45,"") -> 17620
A46: 05.12.00 | B46: F/I P4 Posts At Basement And Module Bearing Lines [P4 - HSS 5x5x1/4"] (House) -- Ref: S-RL A1.10, S-RL A1.11 | C46: 1249.6 | D46: EA | E46: 5 | F46: =IF(AND(ISNUMBER($C46),ISNUMBER($E46)),$C46*$E46,"") -> 6248
A47: 05.12.00 | B47: F/I P5 Posts At Garage And Garage Storage [P5 - HSS 5x5x1/2"] (Garage) -- Ref: S-RL A1.11, S-RL A1.12 | C47: 852.9 | D47: EA | E47: 5 | F47: =IF(AND(ISNUMBER($C47),ISNUMBER($E47)),$C47*$E47,"") -> 4264.5
A48: 05.12.00 | B48: F/I Steel WF Columns On Pile Caps At Rear Deck [STEEL WF COLUMN] (Decks) -- Ref: S-RL A1.10, S-RL A1.11 | C48: 1 | D48: LS | E48: 7636.2 | F48: =IF(AND(ISNUMBER($C48),ISNUMBER($E48)),$C48*$E48,"") -> 7636.2
A49: 05.12.00 | B49: F/I Structural Steel Slats / Columns At Terrace Painted Black To Match Infill Panels [SHOP-APPLIED EPOXY PRIMER & ALIPHATIC POLYURETHANE TOP COAT, OR APPR'D EQ APPROPRIATE FOR HIGH-EXPOSURE ENVIRONMENT.] (Hardscape) -- Ref: A0.10 | D49: INCL | F49: =IF(AND(ISNUMBER($C49),ISNUMBER($E49)),$C49*$E49,"")
A50: TRADE TOTAL | F50: =IF(SUM(F38:F49)=0,"-",SUM(F38:F49)) -> 306086.65 | H50: =IF(SUM(H37:H49)=0,"-",SUM(H37:H49)) -> 330000 | I50: =IF(SUM(I37:I49)=0,"-",SUM(I37:I49)) -> - | J50: =IF(SUM(J37:J49)=0,"-",SUM(J37:J49)) -> - | K50: =IF(SUM(K37:K49)=0,"-",SUM(K37:K49)) -> -
A52: DECORATIVE METAL & RAILINGS | H52: ABCO | I52: Sub #2 | J52: Sub #3 | K52: Sub #4
A54: 05.70.00 | B54: Provide Shop Drawings | C54: 1 | D54: LS | E54: 1500 | F54: =IF(AND(ISNUMBER($C54),ISNUMBER($E54)),$C54*$E54,"") -> 1500
A55: 05.70.00 | B55: F/I MTL-1 Black Steel Cladding At Center Stair Wall, All Sides [14 GA. HOT-ROLLED BLACK STEEL 5'X10' SHEETS] (House) -- Ref: A1.11, 01/A2.21, A0.10 | C55: 300 | D55: SF | E55: 60 | F55: =IF(AND(ISNUMBER($C55),ISNUMBER($E55)),$C55*$E55,"") -> 18000
A56: 05.70.00 | B56: F/I MTL-1 Black Steel At Stair Floor And Slab Edges [14 GA. HOT-ROLLED BLACK STEEL] (House) -- Ref: 02/A2.20, 01/A2.21, A0.10 | C56: 26.93 | D56: SF | E56: 60 | F56: =IF(AND(ISNUMBER($C56),ISNUMBER($E56)),$C56*$E56,"") -> 1615.8
A57: 05.70.00 | B57: F/I MTL-1 Black Steel Wall Cladding At Primary Bedroom 204 [14 GA. HOT-ROLLED BLACK STEEL] (House) -- Ref: 02/A4.03, 03/A4.03, 06/A4.03, A0.10 | C57: 229 | D57: SF | E57: 60 | F57: =IF(AND(ISNUMBER($C57),ISNUMBER($E57)),$C57*$E57,"") -> 13740
A58: 05.70.00 | B58: Clean And Finish MTL-1 Black Steel With Hand-Rubbed Clear Stain And Varnish, Provide Sample For Architect Approval [CLEAN W/DEGREASER & APPLY (2) COATS OLD VILLAGE 1400 CLEAR STAIN & VARNISH (HAND-RUBBED W/CHEESECLOTH OR SIM.)] (House) -- Ref: A0.10 | C58: 543 | D58: SF | E58: 9 | F58: =IF(AND(ISNUMBER($C58),ISNUMBER($E58)),$C58*$E58,"") -> 4887
A59: 05.70.00 | B59: F/I Custom Metal Handrail Brackets Powder-Coated White For Variable Depths At Window Posts And Wall [CUSTOM METAL BRACKETS POWDER-COATED WHITE] (House) -- Ref: 01/A2.20, SUPP Sec. 6.10 | C59: 10 | D59: EA | E59: 250 | F59: =IF(AND(ISNUMBER($C59),ISNUMBER($E59)),$C59*$E59,"") -> 2500
A60: 05.73.00 | B60: Provide Shop Drawings | C60: 1 | D60: EA | E60: 2500 | F60: =IF(AND(ISNUMBER($C60),ISNUMBER($E60)),$C60*$E60,"") -> 2500
A61: 05.73.00 | B61: F/I Exterior Glass Guardrails In Concealed Recessed Base Shoe At Decks And Terrace [11/16" LAMINATED, FULLY TEMPERED LOW-IRON GLASS W/ POLISHED FLAT EDGES & FACTORY-APPLIED HYDROPHOBIC COATING IN RECESSED BASE SHOE] (Decks) -- Ref: A0.10, A1.10-A1.12 Keynote 3, SUPP Sec. 6.6 | C61: 153 | D61: LF | E61: 480 | F61: =IF(AND(ISNUMBER($C61),ISNUMBER($E61)),$C61*$E61,"") -> 73440
A62: 05.73.00 | B62: F/I Glass Guardrails At Roof Deck And Roof Access Stair [11/16" LAMINATED, FULLY TEMPERED LOW-IRON GLASS W/ POLISHED FLAT EDGES & FACTORY-APPLIED HYDROPHOBIC COATING IN RECESSED BASE SHOE] (House) -- Ref: A2.00 Gen. Note 06, SUPP Sec. 8.4, A0.10 | C62: 195 | D62: LF | E62: 480 | F62: =IF(AND(ISNUMBER($C62),ISNUMBER($E62)),$C62*$E62,"") -> 93600
A63: 05.73.00 | B63: F/I MTL-1 @ Stair -- Possible overlap w/ row 57 stair cladding - verify -- Ref: Cost Detail (Almost Complete), added 2026-09-29 | C63: 506.43 | D63: SF | E63: 60 | F63: =IF(AND(ISNUMBER($C63),ISNUMBER($E63)),$C63*$E63,"") -> 30385.8
A64: 05.73.00 | B64: F/I Engineered Blocking For Deck Railings -- Ref: Cost Detail (Almost Complete), added 2026-09-29 | C64: 153.36 | D64: LF | E64: 22 | F64: =IF(AND(ISNUMBER($C64),ISNUMBER($E64)),$C64*$E64,"") -> 3373.92
A65: 05.73.00 | B65: F/I 3x3x.25 Stainless Steel T-Bar 1' Long @ Stair Treads -- Prices unpriced row 66 -- Ref: Cost Detail (Almost Complete), added 2026-09-29 | C65: 14 | D65: EA | E65: 175 | F65: =IF(AND(ISNUMBER($C65),ISNUMBER($E65)),$C65*$E65,"") -> 2450
... A67: 05.73.00 | B67: F/I Steel Center Stringer For Stairs From 1st To 2nd Floor -- Ref: Cost Detail (Almost Complete), added 2026-09-29 | C67: 19 | D67: LF | E67: 250 | F67: =IF(AND(ISNUMBER($C67),ISNUMBER($E67)),$C67*$E67,"") -> 4750
A68: TRADE TOTAL | F68: =IF(SUM(F54:F67)=0,"-",SUM(F54:F67)) -> 257533.52 | H68: =IF(SUM(H53:H67)=0,"-",SUM(H53:H67)) -> - | I68: =IF(SUM(I53:I67)=0,"-",SUM(I53:I67)) -> - | J68: =IF(SUM(J53:J67)=0,"-",SUM(J53:J67)) -> - | K68: =IF(SUM(K53:K67)=0,"-",SUM(K53:K67)) -> -
A70: ROUGH CARPENTRY | H70: SUQUI | I70: Sub #2 | J70: Sub #3 | K70: Sub #4
H71: 72500
A72: 06.10.00 | B72: F/I Framing At Site-Built Stair Volume, Floors And Roof [PER DWGS] (House) -- Ref: A0.10, A0.00 | D72: INCL | F72: =IF(AND(ISNUMBER($C72),ISNUMBER($E72)),$C72*$E72,"")
A73: 06.10.00 | B73: F/I Framing, Sheathing And Structure At Overhangs And Waterproof Decks [OVERHANGS / WATERPROOF DECKS W/ ASSOCIATED FRAMING, STRUCTURE, ROOFING, AND FINISHES AS PER PLANS] (Decks) -- Ref: A0.10 | D73: INCL | F73: =IF(AND(ISNUMBER($C73),ISNUMBER($E73)),$C73*$E73,"")
A74: 06.10.00 | B74: F/I First Floor Deck Framing And Joists [1 3/4"x9 1/4" LVL @ 16" O.C.; 2x10 LVL @ 16" O.C.] (Decks) -- Ref: S-RL A1.11 | C74: 1303.72 | D74: SF | E74: 25 | F74: =IF(AND(ISNUMBER($C74),ISNUMBER($E74)),$C74*$E74,"") -> 32593
A75: 06.10.00 | B75: F/I Second Floor Deck Framing, Beams, Joists And Ledgers [(3) 1 3/4"x9 1/4" LVL; 2x10 @ 16" O.C.; LEDGER] (Decks) -- Ref: S-RL A1.12 | C75: 1 | D75: LS | E75: 44001.15 | F75: =IF(AND(ISNUMBER($C75),ISNUMBER($E75)),$C75*$E75,"") -> 44001.15
A76: 06.10.00 | B76: F/I Site-Built Roof Overhang And Roof Deck Perimeter Framing, Beams, Headers And Ledgers [(3) 1 3/4"x 11 7/8" LVL; (3) 1 3/4"x 9 1/4" LVL; 2x10 @ 16" O.C.; (2) 2x10 LEDGER] (House) -- Ref: S-RL A1.13, A1.12 | C76: 1102.55 | D76: SF | E76: 7.1873982 | F76: =IF(AND(ISNUMBER($C76),ISNUMBER($E76)),$C76*$E76,"") -> 7924.4659
A77: 06.10.00 | B77: Provide Deck And Terrace Slope Framing [ALL DECK SLOPE BY GC TYP.] (Decks) -- Ref: A1.11, A1.12 Plan Notes | D77: INCL | F77: =IF(AND(ISNUMBER($C77),ISNUMBER($E77)),$C77*$E77,"")
A78: 06.10.00 | B78: F/I Covered Deck And Ramp At Outdoor Living [DECK & RAMP BY G.C.] (Decks) -- Ref: 02/A2.00 | D78: INCL | F78: =IF(AND(ISNUMBER($C78),ISNUMBER($E78)),$C78*$E78,"")
A79: 06.10.00 | B79: F/I Roof Overhang Framing At Garage Door And Outdoor Living [ROOF OVERHANG, BY G.C.] (Garage) -- Ref: 02/A2.01, 02/A2.00 | D79: INCL | F79: =IF(AND(ISNUMBER($C79),ISNUMBER($E79)),$C79*$E79,"")
A80: 06.10.00 | B80: F/I Garage Exterior Wall Framing And Sheathing [1/2" ZIP SHEATHING OVER 2X6 FRAMING BY GC, TYP.] (Garage) -- Ref: 01/A3.00, A0.10 | C80: 148.5 | D80: SF | E80: 4.6372538 | F80: =IF(AND(ISNUMBER($C80),ISNUMBER($E80)),$C80*$E80,"") -> 688.63219
A81: 06.10.00 | B81: F/I Garage Roof Framing, Beams And Ledger [14" TJI 360 @ 16" O.C.; (3) 1 3/4"X9 1/2" LVL] (Garage) -- Ref: 01/A3.00, S-RL A1.12 | C81: 1160.3 | D81: SF | E81: 6.1457379 | F81: =IF(AND(ISNUMBER($C81),ISNUMBER($E81)),$C81*$E81,"") -> 7130.8997
A82: 06.10.00 | B82: I/O Factory-Panelized Parapet Walls / Curbs Shipped Loose And Provide Connections With Ply Panel [2X6 FRAMING, 1/2" EXT GRADE PLY. SHEATHING INSIDE AND OUTSIDE (PANELIZED & SHIPPED LOOSE BY FACTORY, ON-SITE INSTALLATION & CONNECTIONS BY GC)] (House) -- Ref: A0.10, A1.10-A1.13 Keynote 7, 02/A3.00, A5.01 Gen. Note 01 | D82: INCL | F82: =IF(AND(ISNUMBER($C82),ISNUMBER($E82)),$C82*$E82,"")
A83: 06.10.00 | B83: F/I Roof Parapets Not Over Modules [Not Specified] (House) -- Ref: A2.00 Keynote 11 | D83: INCL | F83: =IF(AND(ISNUMBER($C83),ISNUMBER($E83)),$C83*$E83,"")
A84: 06.10.00 | B84: F/I Wood Framing For Hung Ceilings And Exterior Sheathing At Stucco Ceilings [Not Specified] (House) -- Ref: A2.00 Keynote 9 | D84: INCL | F84: =IF(AND(ISNUMBER($C84),ISNUMBER($E84)),$C84*$E84,"")
A85: 06.10.00 | B85: F/I 5/8" Plywood Roof Sheathing At Site-Built Roofs [EXTERIOR SHEATHING: 5/8" PLYWOOD] (House) -- Ref: A0.10 | D85: INCL | F85: =IF(AND(ISNUMBER($C85),ISNUMBER($E85)),$C85*$E85,"")
A86: 06.10.00 | B86: F/I Interior Partition Framing Outside Modules [2X4 WOOD STUDS @ 16" O.C., U.O.N.] (House) -- Ref: A0.10 | C86: 218.34 | D86: SF | E86: 1.0478565 | F86: =IF(AND(ISNUMBER($C86),ISNUMBER($E86)),$C86*$E86,"") -> 228.789
A87: 06.10.00 | B87: F/I 2X Stud Framing At Basement Walls To Receive Wall-Mounted Equipment [WALLS TO RECEIVE WALL-MTD EQUIP TO BE FRAMED OUT W/ 2X STUDS AS INDICATED IN PHASE I.] (House) -- Ref: A1.10 | D87: INCL | F87: =IF(AND(ISNUMBER($C87),ISNUMBER($E87)),$C87*$E87,"")
A88: 06.10.00 | B88: F/I Temporary Basement Walls [TEMPORARY WALLS & DOOR IN PHASE 1 (AS HATCHED) - CONFIGURATION TBC] (House) -- Ref: A1.10, SUPP Sec. 2 | D88: INCL | F88: =IF(AND(ISNUMBER($C88),ISNUMBER($E88)),$C88*$E88,"")
A89: 06.10.00 | B89: F/I Pressure Treated Wood Bucks And Plywood Pad-Out At Basement Openings #001, #002, #003 [2X6 P.T. WOOD BUCK, TYP.] (House) -- Ref: 01/A0.24, 02/A0.24, 03/A0.24 | D89: INCL | F89: =IF(AND(ISNUMBER($C89),ISNUMBER($E89)),$C89*$E89,"")
A90: 06.10.00 | B90: F/I Blocking / Framing At Window Heads For Anchoring Tension Cable Rail [BLOCKING / FRAMING AS REQ'D. AT WINDOW HEAD FOR ANCHORING TENSION CABLE RAIL] (House) -- Ref: 01/A2.20 | C90: 15 | D90: LF | E90: 12 | F90: =IF(AND(ISNUMBER($C90),ISNUMBER($E90)),$C90*$E90,"") -> 180
A91: 06.10.00 | B91: F/I Blocking For 1-3/4" Trim Projection Where Window Trim Is Grouped With Adjacent Door Unit [Not Specified] (House) -- Ref: 03/A0.21 | D91: INCL | F91: =IF(AND(ISNUMBER($C91),ISNUMBER($E91)),$C91*$E91,"")
A92: 06.10.00 | B92: F/I Blocking For Wall-Mounted TV Locations Outside Modules [Not Specified] (House) -- Ref: A1.30 Elec. Note 09 | D92: INCL | F92: =IF(AND(ISNUMBER($C92),ISNUMBER($E92)),$C92*$E92,"")
A93: 06.10.00 | B93: F/I Double 2x8 Sill Plates With Bolts For Modular Attachment -- Prices unpriced row 71 -- Ref: Cost Detail (Almost Complete), added 2026-09-29 | C93: 164.3 | D93: LF | E93: 14 | F93: =IF(AND(ISNUMBER($C93),ISNUMBER($E93)),$C93*$E93,"") -> 2300.2
A94: 06.10.00 | B94: 2x6x12' Studs [Site-Built Exterior Walls] -- Ref: Cost Detail (Almost Complete), added 2026-09-29 | C94: 119 | D94: EA | E94: 23.19 | F94: =IF(AND(ISNUMBER($C94),ISNUMBER($E94)),$C94*$E94,"") -> 2759.61
A95: 06.10.00 | B95: 2x6 Top Plates [Site-Built Exterior Walls] -- Ref: Cost Detail (Almost Complete), added 2026-09-29 | C95: 236.54 | D95: LF | E95: 1.94 | F95: =IF(AND(ISNUMBER($C95),ISNUMBER($E95)),$C95*$E95,"") -> 458.8876
A96: 06.10.00 | B96: 2x6 Bottom Plates [Site-Built Exterior Walls] -- Ref: Cost Detail (Almost Complete), added 2026-09-29 | C96: 118.27 | D96: LF | E96: 1.94 | F96: =IF(AND(ISNUMBER($C96),ISNUMBER($E96)),$C96*$E96,"") -> 229.4438
A97: 06.10.00 | B97: Zip 1/2" Sheathing (4x12) [Site-Built Exterior Walls] -- Ref: Cost Detail (Almost Complete), added 2026-09-29 | C97: 30 | D97: EA | E97: 63.59 | F97: =IF(AND(ISNUMBER($C97),ISNUMBER($E97)),$C97*$E97,"") -> 1907.7
A98: 06.10.00 | B98: 2x4x9' Studs [Interior Partitions] -- Ref: Cost Detail (Almost Complete), added 2026-09-29 | C98: 30 | D98: EA | E98: 12.16 | F98: =IF(AND(ISNUMBER($C98),ISNUMBER($E98)),$C98*$E98,"") -> 364.8
A99: 06.10.00 | B99: 2x4 Top Plates [Interior Partitions] -- Ref: Cost Detail (Almost Complete), added 2026-09-29 | C99: 59.16 | D99: LF | E99: 1.94 | F99: =IF(AND(ISNUMBER($C99),ISNUMBER($E99)),$C99*$E99,"") -> 114.7704
A100: 06.10.00 | B100: 2x4 Bottom Plates [Interior Partitions] -- Ref: Cost Detail (Almost Complete), added 2026-09-29 | C100: 29.58 | D100: LF | E100: 1.94 | F100: =IF(AND(ISNUMBER($C100),ISNUMBER($E100)),$C100*$E100,"") -> 57.3852
A101: 06.10.00 | B101: 2x4x9' Studs [Misc. Framing] -- Ref: Cost Detail (Almost Complete), added 2026-09-29 | C101: 11 | D101: EA | E101: 12.16 | F101: =IF(AND(ISNUMBER($C101),ISNUMBER($E101)),$C101*$E101,"") -> 133.76
A102: 06.10.00 | B102: 2x4 Top Plates [Misc. Framing] -- Ref: Cost Detail (Almost Complete), added 2026-09-29 | C102: 21.56 | D102: LF | E102: 1.94 | F102: =IF(AND(ISNUMBER($C102),ISNUMBER($E102)),$C102*$E102,"") -> 41.8264
A103: 06.10.00 | B103: 2x4 Bottom Plates [Misc. Framing] -- Ref: Cost Detail (Almost Complete), added 2026-09-29 | C103: 10.78 | D103: LF | E103: 1.94 | F103: =IF(AND(ISNUMBER($C103),ISNUMBER($E103)),$C103*$E103,"") -> 20.9132
A104: 06.10.00 | B104: 2x6x9' Studs [Misc. Framing] -- Ref: Cost Detail (Almost Complete), added 2026-09-29 | C104: 25 | D104: EA | E104: 17.4 | F104: =IF(AND(ISNUMBER($C104),ISNUMBER($E104)),$C104*$E104,"") -> 435
... A106: 06.10.00 | B106: 2x6 Bottom Plates [Misc. Framing] -- Ref: Cost Detail (Almost Complete), added 2026-09-29 | C106: 24.88 | D106: LF | E106: 1.94 | F106: =IF(AND(ISNUMBER($C106),ISNUMBER($E106)),$C106*$E106,"") -> 48.2672
A107: TRADE TOTAL | F107: =IF(SUM(F72:F106)=0,"-",SUM(F72:F106)) -> 101716.04 | H107: =IF(SUM(H71:H106)=0,"-",SUM(H71:H106)) -> 72500 | I107: =IF(SUM(I71:I106)=0,"-",SUM(I71:I106)) -> - | J107: =IF(SUM(J71:J106)=0,"-",SUM(J71:J106)) -> - | K107: =IF(SUM(K71:K106)=0,"-",SUM(K71:K106)) -> -
A109: DECKING | H109: Sub #1 | I109: Sub #2 | J109: Sub #3 | K109: Sub #4
A111: 06.15.00 | B111: F/I FL-2 Ipe Decking At First And Second Floor Decks With Concealed Fasteners [IPE, PRE-GROOVED 5/4 X 6 W/ CONCEALED FASTENERS (TIGERCLAW OR SIM.)] (Decks) -- Ref: A0.10 Finish Sch., A1.41, A1.42 | C111: =2405.66*1.1 -> 2646.226 | D111: SF | E111: 26 | F111: =IF(AND(ISNUMBER($C111),ISNUMBER($E111)),$C111*$E111,"") -> 68801.876
A112: 06.10.00 | B112: F/I Deck Pedestals / Sleepers Over EPDM At Decks Over Roofing [Not Specified] (Decks) -- Ref: 10/A5.00 | C112: =2405.66*1.1 -> 2646.226 | D112: SF | E112: 11 | F112: =IF(AND(ISNUMBER($C112),ISNUMBER($E112)),$C112*$E112,"") -> 29108.486
A113: 06.15.00 | B113: Provide Samples Of Decking For Owner / Architect Approval [Not Specified] (Decks) -- Ref: A0.10 Finish Sch. | C113: 1 | D113: LS | E113: 3 | F113: =IF(AND(ISNUMBER($C113),ISNUMBER($E113)),$C113*$E113,"") -> 3
...

Sheet SOV
A1: Eun/Yu Residence -- 28 Country Club Lane South -- Schedule of Values
A2: Job E26040 | 28 Country Club Lane South, Briarcliff Manor, NY 10510 | BLDG Estimating | 2026-09-23
A3: Our Total and the sub columns link to the Estimate sheet. Final Price is entered by hand per trade and runs through the same Subtotal / General Conditions / Fee / Insurance ladder. Markup percentages are entered once on the Estimate sheet. The low sub bid in each row is highlighted.
A5: CSI | B5: Trade | C5: Our Total | D5: Final Price | E5: Sub #1 | F5: Sub #2 | G5: Sub #3 | H5: Sub #4 | I5: Low Bid | J5: Low Bidder | K5: Low Bid vs Ours
A6: 03.30.00, 03.40.00 | B6: Concrete | C6: =Estimate!F34 -> 131662.69 | D6: 149900 | E6: =IF(Estimate!H34="-","",Estimate!H34) | F6: =IF(Estimate!I34="-","",Estimate!I34) | G6: =IF(Estimate!J34="-","",Estimate!J34) | H6: =IF(Estimate!K34="-","",Estimate!K34) | I6: =IF(COUNT(E6:H6)=0,"",MIN(E6:H6)) | J6: =IF(I6="","",INDEX($E$5:$H$5,MATCH(I6,E6:H6,0))) | K6: =IF(OR(I6="",N(C6)=0),"",I6-C6)
A7: 05.12.00 | B7: Structural Steel | C7: =Estimate!F50 -> 306086.65 | D7: =ROUND(E7,0) -> 330000 | E7: =IF(Estimate!H50="-","",Estimate!H50) -> 330000 | F7: =IF(Estimate!I50="-","",Estimate!I50) | G7: =IF(Estimate!J50="-","",Estimate!J50) | H7: =IF(Estimate!K50="-","",Estimate!K50) | I7: =IF(COUNT(E7:H7)=0,"",MIN(E7:H7)) -> 330000 | J7: =IF(I7="","",INDEX($E$5:$H$5,MATCH(I7,E7:H7,0))) -> Sub #1 | K7: =IF(OR(I7="",N(C7)=0),"",I7-C7) -> 23913.35
A8: 05.70.00, 05.73.00 | B8: Decorative Metal & Railings | C8: =Estimate!F68 -> 257533.52 | D8: =ROUND(C8,0) -> 257534 | E8: =IF(Estimate!H68="-","",Estimate!H68) | F8: =IF(Estimate!I68="-","",Estimate!I68) | G8: =IF(Estimate!J68="-","",Estimate!J68) | H8: =IF(Estimate!K68="-","",Estimate!K68) | I8: =IF(COUNT(E8:H8)=0,"",MIN(E8:H8)) | J8: =IF(I8="","",INDEX($E$5:$H$5,MATCH(I8,E8:H8,0))) | K8: =IF(OR(I8="",N(C8)=0),"",I8-C8)
A9: 06.10.00 | B9: Rough Carpentry | C9: =Estimate!F107 -> 101716.04 | D9: =ROUND(E9+50000,0) -> 122500 | E9: =IF(Estimate!H107="-","",Estimate!H107) -> 72500 | F9: =IF(Estimate!I107="-","",Estimate!I107) | G9: =IF(Estimate!J107="-","",Estimate!J107) | H9: =IF(Estimate!K107="-","",Estimate!K107) | I9: =IF(COUNT(E9:H9)=0,"",MIN(E9:H9)) -> 72500 | J9: =IF(I9="","",INDEX($E$5:$H$5,MATCH(I9,E9:H9,0))) -> Sub #1 | K9: =IF(OR(I9="",N(C9)=0),"",I9-C9) -> -29216.035
A10: 06.15.00 | B10: Decking | C10: =Estimate!F115 -> 105113.36 | D10: =ROUND(C10,0) -> 105113 | E10: =IF(Estimate!H115="-","",Estimate!H115) | F10: =IF(Estimate!I115="-","",Estimate!I115) | G10: =IF(Estimate!J115="-","",Estimate!J115) | H10: =IF(Estimate!K115="-","",Estimate!K115) | I10: =IF(COUNT(E10:H10)=0,"",MIN(E10:H10)) | J10: =IF(I10="","",INDEX($E$5:$H$5,MATCH(I10,E10:H10,0))) | K10: =IF(OR(I10="",N(C10)=0),"",I10-C10)
A11: 06.20.00, 06.43.00 | B11: Finish Carpentry & Stairs | C11: =Estimate!F129 -> 108426.54 | D11: 115756 | E11: =IF(Estimate!H129="-","",Estimate!H129) | F11: =IF(Estimate!I129="-","",Estimate!I129) | G11: =IF(Estimate!J129="-","",Estimate!J129) | H11: =IF(Estimate!K129="-","",Estimate!K129) | I11: =IF(COUNT(E11:H11)=0,"",MIN(E11:H11)) | J11: =IF(I11="","",INDEX($E$5:$H$5,MATCH(I11,E11:H11,0))) | K11: =IF(OR(I11="",N(C11)=0),"",I11-C11)
A12: 06.40.00 | B12: Closet Interiors (Allowance) | C12: =Estimate!F142 -> 33000 | D12: =ROUND(C12,0) -> 33000 | E12: =IF(Estimate!H142="-","",Estimate!H142) | F12: =IF(Estimate!I142="-","",Estimate!I142) | G12: =IF(Estimate!J142="-","",Estimate!J142) | H12: =IF(Estimate!K142="-","",Estimate!K142) | I12: =IF(COUNT(E12:H12)=0,"",MIN(E12:H12)) | J12: =IF(I12="","",INDEX($E$5:$H$5,MATCH(I12,E12:H12,0))) | K12: =IF(OR(I12="",N(C12)=0),"",I12-C12)
A13: 06.40.00 | B13: Custom Millwork | C13: =Estimate!F154 -> 34682 | D13: =ROUND(C13,0) -> 34682 | E13: =IF(Estimate!H154="-","",Estimate!H154) | F13: =IF(Estimate!I154="-","",Estimate!I154) | G13: =IF(Estimate!J154="-","",Estimate!J154) | H13: =IF(Estimate!K154="-","",Estimate!K154) | I13: =IF(COUNT(E13:H13)=0,"",MIN(E13:H13)) | J13: =IF(I13="","",INDEX($E$5:$H$5,MATCH(I13,E13:H13,0))) | K13: =IF(OR(I13="",N(C13)=0),"",I13-C13)
A14: 07.10.00, 33.46.00 | B14: Waterproofing & Foundation Drainage | C14: =Estimate!F161 -> 7887.4 | D14: 9000 | E14: =IF(Estimate!H161="-","",Estimate!H161) | F14: =IF(Estimate!I161="-","",Estimate!I161) | G14: =IF(Estimate!J161="-","",Estimate!J161) | H14: =IF(Estimate!K161="-","",Estimate!K161) | I14: =IF(COUNT(E14:H14)=0,"",MIN(E14:H14)) | J14: =IF(I14="","",INDEX($E$5:$H$5,MATCH(I14,E14:H14,0))) | K14: =IF(OR(I14="",N(C14)=0),"",I14-C14)
A15: 07.21.00 | B15: Insulation | C15: =Estimate!F174 -> 52719.943 | D15: =ROUND(C15,0) -> 52720 | E15: =IF(Estimate!H174="-","",Estimate!H174) | F15: =IF(Estimate!I174="-","",Estimate!I174) | G15: =IF(Estimate!J174="-","",Estimate!J174) | H15: =IF(Estimate!K174="-","",Estimate!K174) | I15: =IF(COUNT(E15:H15)=0,"",MIN(E15:H15)) | J15: =IF(I15="","",INDEX($E$5:$H$5,MATCH(I15,E15:H15,0))) | K15: =IF(OR(I15="",N(C15)=0),"",I15-C15)
A16: 07.24.00, 09.24.00 | B16: EIFS & Stucco | C16: =Estimate!F183 -> 149019.71 | D16: =ROUND(C16,0) -> 149020 | E16: =IF(Estimate!H183="-","",Estimate!H183) | F16: =IF(Estimate!I183="-","",Estimate!I183) | G16: =IF(Estimate!J183="-","",Estimate!J183) | H16: =IF(Estimate!K183="-","",Estimate!K183) | I16: =IF(COUNT(E16:H16)=0,"",MIN(E16:H16)) | J16: =IF(I16="","",INDEX($E$5:$H$5,MATCH(I16,E16:H16,0))) | K16: =IF(OR(I16="",N(C16)=0),"",I16-C16)
A17: 07.25.00, 07.46.00 | B17: Siding & Weather Barriers | C17: =Estimate!F198 -> 186515.34 | D17: =ROUND(C17,0) -> 186515 | E17: =IF(Estimate!H198="-","",Estimate!H198) | F17: =IF(Estimate!I198="-","",Estimate!I198) | G17: =IF(Estimate!J198="-","",Estimate!J198) | H17: =IF(Estimate!K198="-","",Estimate!K198) | I17: =IF(COUNT(E17:H17)=0,"",MIN(E17:H17)) | J17: =IF(I17="","",INDEX($E$5:$H$5,MATCH(I17,E17:H17,0))) | K17: =IF(OR(I17="",N(C17)=0),"",I17-C17)
A18: 07.33.63, 07.53.23, 07.62.00 | B18: Roofing & Sheet Metal | C18: =Estimate!F220 -> 149249.24 | D18: =ROUND(32350+51250+38610+22500+23125+6525,0) -> 174360 | E18: =IF(Estimate!H220="-","",Estimate!H220) | F18: =IF(Estimate!I220="-","",Estimate!I220) | G18: =IF(Estimate!J220="-","",Estimate!J220) | H18: =IF(Estimate!K220="-","",Estimate!K220) | I18: =IF(COUNT(E18:H18)=0,"",MIN(E18:H18)) | J18: =IF(I18="","",INDEX($E$5:$H$5,MATCH(I18,E18:H18,0))) | K18: =IF(OR(I18="",N(C18)=0),"",I18-C18)
A19: 08.14.16, 08.71.00 | B19: Doors, Frames & Hardware | C19: =Estimate!F232 -> 27440 | D19: 28500 | E19: =IF(Estimate!H232="-","",Estimate!H232) | F19: =IF(Estimate!I232="-","",Estimate!I232) | G19: =IF(Estimate!J232="-","",Estimate!J232) | H19: =IF(Estimate!K232="-","",Estimate!K232) | I19: =IF(COUNT(E19:H19)=0,"",MIN(E19:H19)) | J19: =IF(I19="","",INDEX($E$5:$H$5,MATCH(I19,E19:H19,0))) | K19: =IF(OR(I19="",N(C19)=0),"",I19-C19)
A20: 08.36.13 | B20: Overhead Garage Door | C20: =Estimate!F238 -> 14100 | D20: =ROUND(C20,0) -> 14100 | E20: =IF(Estimate!H238="-","",Estimate!H238) | F20: =IF(Estimate!I238="-","",Estimate!I238) | G20: =IF(Estimate!J238="-","",Estimate!J238) | H20: =IF(Estimate!K238="-","",Estimate!K238) | I20: =IF(COUNT(E20:H20)=0,"",MIN(E20:H20)) | J20: =IF(I20="","",INDEX($E$5:$H$5,MATCH(I20,E20:H20,0))) | K20: =IF(OR(I20="",N(C20)=0),"",I20-C20)
A21: 08.50.00 | B21: Windows | C21: =Estimate!F245 -> 41300 | D21: =ROUND(C21,0) -> 41300 | E21: =IF(Estimate!H245="-","",Estimate!H245) -> 41286.61 | F21: =IF(Estimate!I245="-","",Estimate!I245) | G21: =IF(Estimate!J245="-","",Estimate!J245) | H21: =IF(Estimate!K245="-","",Estimate!K245) | I21: =IF(COUNT(E21:H21)=0,"",MIN(E21:H21)) -> 41286.61 | J21: =IF(I21="","",INDEX($E$5:$H$5,MATCH(I21,E21:H21,0))) -> Sub #1 | K21: =IF(OR(I21="",N(C21)=0),"",I21-C21) -> -13.39
A22: 08.80.00, 08.83.00 | B22: Glass & Glazing | C22: =Estimate!F255 -> 23787.65 | D22: =ROUND(C22,0) -> 23788 | E22: =IF(Estimate!H255="-","",Estimate!H255) | F22: =IF(Estimate!I255="-","",Estimate!I255) | G22: =IF(Estimate!J255="-","",Estimate!J255) | H22: =IF(Estimate!K255="-","",Estimate!K255) | I22: =IF(COUNT(E22:H22)=0,"",MIN(E22:H22)) | J22: =IF(I22="","",INDEX($E$5:$H$5,MATCH(I22,E22:H22,0))) | K22: =IF(OR(I22="",N(C22)=0),"",I22-C22)
A23: 09.20.00 | B23: Drywall & Carpentry | C23: =Estimate!F280 -> 32547.622 | D23: =ROUND(C23,0) -> 32548 | E23: =IF(Estimate!H280="-","",Estimate!H280) | F23: =IF(Estimate!I280="-","",Estimate!I280) | G23: =IF(Estimate!J280="-","",Estimate!J280) | H23: =IF(Estimate!K280="-","",Estimate!K280) | I23: =IF(COUNT(E23:H23)=0,"",MIN(E23:H23)) | J23: =IF(I23="","",INDEX($E$5:$H$5,MATCH(I23,E23:H23,0))) | K23: =IF(OR(I23="",N(C23)=0),"",I23-C23)
A24: 09.30.00 | B24: Tile | C24: =Estimate!F288 -> 44713.6 | D24: 54000 | E24: =IF(Estimate!H288="-","",Estimate!H288) | F24: =IF(Estimate!I288="-","",Estimate!I288) | G24: =IF(Estimate!J288="-","",Estimate!J288) | H24: =IF(Estimate!K288="-","",Estimate!K288) | I24: =IF(COUNT(E24:H24)=0,"",MIN(E24:H24)) | J24: =IF(I24="","",INDEX($E$5:$H$5,MATCH(I24,E24:H24,0))) | K24: =IF(OR(I24="",N(C24)=0),"",I24-C24)
A25: 09.64.00 | B25: Wood Flooring | C25: =Estimate!F294 -> 26655.62 | D25: =ROUND(C25,0) -> 26656 | E25: =IF(Estimate!H294="-","",Estimate!H294) | F25: =IF(Estimate!I294="-","",Estimate!I294) | G25: =IF(Estimate!J294="-","",Estimate!J294) | H25: =IF(Estimate!K294="-","",Estimate!K294) | I25: =IF(COUNT(E25:H25)=0,"",MIN(E25:H25)) | J25: =IF(I25="","",INDEX($E$5:$H$5,MATCH(I25,E25:H25,0))) | K25: =IF(OR(I25="",N(C25)=0),"",I25-C25)
A26: 09.90.00 | B26: Painting | C26: =Estimate!F312 -> 73284.087 | D26: =ROUND(C26,0) -> 73284 | E26: =IF(Estimate!H312="-","",Estimate!H312) | F26: =IF(Estimate!I312="-","",Estimate!I312) | G26: =IF(Estimate!J312="-","",Estimate!J312) | H26: =IF(Estimate!K312="-","",Estimate!K312) | I26: =IF(COUNT(E26:H26)=0,"",MIN(E26:H26)) | J26: =IF(I26="","",INDEX($E$5:$H$5,MATCH(I26,E26:H26,0))) | K26: =IF(OR(I26="",N(C26)=0),"",I26-C26)
A27: 10.28.13 | B27: Specialties | C27: =Estimate!F320 -> 4855 | D27: =ROUND(C27,0) -> 4855 | E27: =IF(Estimate!H320="-","",Estimate!H320) | F27: =IF(Estimate!I320="-","",Estimate!I320) | G27: =IF(Estimate!J320="-","",Estimate!J320) | H27: =IF(Estimate!K320="-","",Estimate!K320) | I27: =IF(COUNT(E27:H27)=0,"",MIN(E27:H27)) | J27: =IF(I27="","",INDEX($E$5:$H$5,MATCH(I27,E27:H27,0))) | K27: =IF(OR(I27="",N(C27)=0),"",I27-C27)
A28: 11.31.00 | B28: Appliances | C28: =Estimate!F330 -> 83450 | D28: =ROUND(C28,0) -> 83450 | E28: =IF(Estimate!H330="-","",Estimate!H330) -> 80871.24 | F28: =IF(Estimate!I330="-","",Estimate!I330) | G28: =IF(Estimate!J330="-","",Estimate!J330) | H28: =IF(Estimate!K330="-","",Estimate!K330) | I28: =IF(COUNT(E28:H28)=0,"",MIN(E28:H28)) -> 80871.24 | J28: =IF(I28="","",INDEX($E$5:$H$5,MATCH(I28,E28:H28,0))) -> Sub #1 | K28: =IF(OR(I28="",N(C28)=0),"",I28-C28) -> -2578.76
A29: 12.36.00 | B29: Countertops | C29: =Estimate!F336 -> 41512 | D29: =ROUND(C29,0) -> 41512 | E29: =IF(Estimate!H336="-","",Estimate!H336) | F29: =IF(Estimate!I336="-","",Estimate!I336) | G29: =IF(Estimate!J336="-","",Estimate!J336) | H29: =IF(Estimate!K336="-","",Estimate!K336) | I29: =IF(COUNT(E29:H29)=0,"",MIN(E29:H29)) | J29: =IF(I29="","",INDEX($E$5:$H$5,MATCH(I29,E29:H29,0))) | K29: =IF(OR(I29="",N(C29)=0),"",I29-C29)
A30: 13.42.00 | B30: Modular Package | C30: =Estimate!F350 -> 1085479.8 | D30: =ROUNDUP(1044419.84,0) -> 1044420 | F30: =IF(Estimate!I350="-","",Estimate!I350) | G30: =IF(Estimate!J350="-","",Estimate!J350) | H30: =IF(Estimate!K350="-","",Estimate!K350) | I30: =IF(COUNT(E30:H30)=0,"",MIN(E30:H30)) | J30: =IF(I30="","",INDEX($E$5:$H$5,MATCH(I30,E30:H30,0))) | K30: =IF(OR(I30="",N(C30)=0),"",I30-C30)
B31: Modular Setting | D31: =ROUND(E31,0) -> 19660 | E31: 19660
A32: 22.11.16, 22.13.16, 22.14.29, 22.34.00, 22.40.00, 23.11.23 | B32: Plumbing & Gas | C32: =Estimate!F371 -> 65300 | D32: 97030 | F32: =IF(Estimate!I371="-","",Estimate!I371) | G32: =IF(Estimate!J371="-","",Estimate!J371) | H32: =IF(Estimate!K371="-","",Estimate!K371) | I32: =IF(COUNT(E32:H32)=0,"",MIN(E32:H32)) | J32: =IF(I32="","",INDEX($E$5:$H$5,MATCH(I32,E32:H32,0))) | K32: =IF(OR(I32="",N(C32)=0),"",I32-C32)
A33: 23.30.00, 23.81.46 | B33: HVAC (Allowance) | C33: =Estimate!F387 -> 196200 | D33: 160000 | E33: =IF(Estimate!H387="-","",Estimate!H387) | F33: =IF(Estimate!I387="-","",Estimate!I387) | G33: =IF(Estimate!J387="-","",Estimate!J387) | H33: =IF(Estimate!K387="-","",Estimate!K387) | I33: =IF(COUNT(E33:H33)=0,"",MIN(E33:H33)) | J33: =IF(I33="","",INDEX($E$5:$H$5,MATCH(I33,E33:H33,0))) | K33: =IF(OR(I33="",N(C33)=0),"",I33-C33)
A34: 26.05.19, 26.09.23, 26.21.00, 26.24.16, 26.27.26, 26.51.13, 26.56.00 | B34: Electrical | C34: =Estimate!F446 -> 230950 | D34: =ROUND(C34,0) -> 230950 | E34: =IF(Estimate!H446="-","",Estimate!H446) | F34: =IF(Estimate!I446="-","",Estimate!I446) | G34: =IF(Estimate!J446="-","",Estimate!J446) | H34: =IF(Estimate!K446="-","",Estimate!K446) | I34: =IF(COUNT(E34:H34)=0,"",MIN(E34:H34)) | J34: =IF(I34="","",INDEX($E$5:$H$5,MATCH(I34,E34:H34,0))) | K34: =IF(OR(I34="",N(C34)=0),"",I34-C34)
A35: 31.10.00, 31.20.00, 31.25.00, 31.50.00, 33.10.00, 33.30.00, 33.40.00 | B35: Sitework | C35: =Estimate!F487 -> 175530.88 | D35: 279000 | E35: =IF(Estimate!H487="-","",Estimate!H487) -> 233765.39 | F35: =IF(Estimate!I487="-","",Estimate!I487) | G35: =IF(Estimate!J487="-","",Estimate!J487) | H35: =IF(Estimate!K487="-","",Estimate!K487) | I35: =IF(COUNT(E35:H35)=0,"",MIN(E35:H35)) -> 233765.39 | J35: =IF(I35="","",INDEX($E$5:$H$5,MATCH(I35,E35:H35,0))) -> Sub #1 | K35: =IF(OR(I35="",N(C35)=0),"",I35-C35) -> 58234.515
B36: Site Demolition | C36: =Estimate!F497 -> 37693.48 | D36: =ROUND(C36,0) -> 37693
A37: 31.66.15 | B37: Helical Piles | C37: =Estimate!F503 -> 28000 | D37: =E37 -> 16000 | E37: =IF(Estimate!H503="-","",Estimate!H503) -> 16000 | F37: =IF(Estimate!I503="-","",Estimate!I503) | G37: =IF(Estimate!J503="-","",Estimate!J503) | H37: =IF(Estimate!K503="-","",Estimate!K503) | I37: =IF(COUNT(E37:H37)=0,"",MIN(E37:H37)) -> 16000 | J37: =IF(I37="","",INDEX($E$5:$H$5,MATCH(I37,E37:H37,0))) -> Sub #1 | K37: =IF(OR(I37="",N(C37)=0),"",I37-C37) -> -12000
A38: 32.14.00, 32.32.00 | B38: Hardscape & Retaining Walls | C38: =Estimate!F513 -> 188512.09 | D38: =ROUND(C38,0) -> 188512 | E38: =IF(Estimate!H513="-","",Estimate!H513) | F38: =IF(Estimate!I513="-","",Estimate!I513) | G38: =IF(Estimate!J513="-","",Estimate!J513) | H38: =IF(Estimate!K513="-","",Estimate!K513) | I38: =IF(COUNT(E38:H38)=0,"",MIN(E38:H38)) | J38: =IF(I38="","",INDEX($E$5:$H$5,MATCH(I38,E38:H38,0))) | K38: =IF(OR(I38="",N(C38)=0),"",I38-C38)
A39: SUBTOTAL | C39: =SUM(C6:C38) -> 4044924.3 | D39: =IF(SUM(D6:D38)=0,"",SUM(D6:D38)) -> 4217358 | E39: =IF(SUM(E6:E38)=0,"",SUM(E6:E38)) -> 794083.24 | F39: =IF(SUM(F6:F38)=0,"",SUM(F6:F38)) | G39: =IF(SUM(G6:G38)=0,"",SUM(G6:G38)) | H39: =IF(SUM(H6:H38)=0,"",SUM(H6:H38))
A40: =Estimate!A516 -> General Conditions | B40: 0.07 | C40: =ROUND((SUM(C39))*$B40,2) -> 283144.7 | D40: =ROUND((SUM(D39))*$B40,0) -> 295215 | E40: =IF(SUM(E39)=0,"",ROUND((SUM(E39))*$B40,2)) -> 55585.83 | F40: =IF(SUM(F39)=0,"",ROUND((SUM(F39))*$B40,2)) | G40: =IF(SUM(G39)=0,"",ROUND((SUM(G39))*$B40,2)) | H40: =IF(SUM(H39)=0,"",ROUND((SUM(H39))*$B40,2))
A41: =Estimate!A517 -> Fee | B41: =Estimate!$E$517 -> 0.06 | C41: =ROUND((SUM(C39)+SUM(C40:C40))*$B41,2) -> 259684.14 | D41: =ROUND((SUM(D39)+SUM(D40:D40))*$B41,0) -> 270754 | E41: =IF(SUM(E39)=0,"",ROUND((SUM(E39)+SUM(E40:E40))*$B41,2)) -> 50980.14 | F41: =IF(SUM(F39)=0,"",ROUND((SUM(F39)+SUM(F40:F40))*$B41,2)) | G41: =IF(SUM(G39)=0,"",ROUND((SUM(G39)+SUM(G40:G40))*$B41,2)) | H41: =IF(SUM(H39)=0,"",ROUND((SUM(H39)+SUM(H40:H40))*$B41,2))
A42: =Estimate!A518 -> Insurance | B42: =Estimate!$E$518 -> 0.0275 | C42: =ROUND((SUM(C39)+SUM(C40:C41))*$B42,2) -> 126163.21 | D42: =ROUND((SUM(D39)+SUM(D40:D41))*$B42,0) -> 131541 | E42: =IF(SUM(E39)=0,"",ROUND((SUM(E39)+SUM(E40:E41))*$B42,2)) -> 24767.85 | F42: =IF(SUM(F39)=0,"",ROUND((SUM(F39)+SUM(F40:F41))*$B42,2)) | G42: =IF(SUM(G39)=0,"",ROUND((SUM(G39)+SUM(G40:G41))*$B42,2)) | H42: =IF(SUM(H39)=0,"",ROUND((SUM(H39)+SUM(H40:H41))*$B42,2))
A43: TOTAL -- BASE BID | C43: =ROUND(SUM(C39,C40:C42),2) -> 4713916.3 | D43: =ROUND(SUM(D39,D40:D42),0) -> 4914868 | E43: =IF(SUM(E39,E40:E42)=0,"",ROUND(SUM(E39,E40:E42),2)) -> 925417.06 | F43: =IF(SUM(F39,F40:F42)=0,"",ROUND(SUM(F39,F40:F42),2)) | G43: =IF(SUM(G39,G40:G42)=0,"",ROUND(SUM(G39,G40:G42),2)) | H43: =IF(SUM(H39,H40:H42)=0,"",ROUND(SUM(H39,H40:H42),2))
A46: ALTERNATES
A47: Our Direct links to the alternate blocks on the Estimate sheet (row 501 on). Enter a Final Price (direct cost) to override ours: General Conditions, Fee and Insurance then compound on the Final Price. Variance = Proposal Amount minus Burdened Total. Red rows are priced but not on the issued proposal.
A48: CSI | B48: Alternate | C48: Our Direct | D48: Final Price | E48: General Conditions | F48: Fee | G48: Insurance | H48: Burdened Total | I48: Proposal Amount | J48: Variance | K48: Proposal Ref
A49: 02.41.16, 26.05.19 | B49: Alternate 1 -- Demolition of Existing House | C49: =SUM(Estimate!F539) -> 63196.92 | D49: =ROUND(Estimate!F543,0) -> 73993 | H49: =ROUND(IF(ISNUMBER(D49),D49,C49)+E49+F49+G49,2) -> 73993 | J49: =IF(I49="","",I49-H49) | K49: Not issued
A50: 31.20.00 | B50: Alternate 2 -- Rough Grading and Structural Fill from El. 52.5 Up [TBD] | C50: =SUM(Estimate!F548) -> 0 | H50: =ROUND(IF(ISNUMBER(D50),D50,C50)+E50+F50+G50,2) -> 0 | J50: =IF(I50="","",I50-H50) | K50: Not issued
A51: 33.40.00 | B51: Alternate 3 -- CULTEC System and Site Drainage | C51: =SUM(Estimate!F564) -> 87624.46 | D51: =ROUND(Estimate!F568,0) -> 102594 | H51: =ROUND(IF(ISNUMBER(D51),D51,C51)+E51+F51+G51,2) -> 102594 | J51: =IF(I51="","",I51-H51) | K51: Not issued
A52: 05.73.00 | B52: Alternate 4 -- Deduct -- Cable Railings in Lieu of Glass | C52: =SUM(Estimate!F574) -> -62640 | D52: =ROUND(Estimate!F578,0) -> -73341 | H52: =ROUND(IF(ISNUMBER(D52),D52,C52)+E52+F52+G52,2) -> -73341 | J52: =IF(I52="","",I52-H52) | K52: Not issued
A53: 06.15.00, 07.46.00, 13.17.00, 26.05.19 | B53: Alternate 5 -- Upper Roof Deck (Cedar, Ipe, Hot Tub) | C53: =SUM(Estimate!F589) -> 90389.82 | D53: =ROUND(Estimate!F593,0) -> 105832 | H53: =ROUND(IF(ISNUMBER(D53),D53,C53)+E53+F53+G53,2) -> 105832 | J53: =IF(I53="","",I53-H53) | K53: Not issued
A54: 07.33.63 | B54: Alternate 6 -- Green Roofs with Irrigation | C54: =SUM(Estimate!F600) -> 76730.55 | D54: =ROUND(Estimate!F604,0) -> 89839 | H54: =ROUND(IF(ISNUMBER(D54),D54,C54)+E54+F54+G54,2) -> 89839 | J54: =IF(I54="","",I54-H54) | K54: Not issued
A55: 26.31.00 | B55: Alternate 7 -- Rooftop Solar Panels | C55: =SUM(Estimate!F615) -> 93000 | D55: =ROUND(Estimate!F619,0) -> 108888 | H55: =ROUND(IF(ISNUMBER(D55),D55,C55)+E55+F55+G55,2) -> 108888 | J55: =IF(I55="","",I55-H55) | K55: Not issued
A56: 26.33.00 | B56: Alternate 8 -- Solar Battery Backup | C56: =SUM(Estimate!F627) -> 17000 | D56: =ROUND(Estimate!F631,0) -> 19904 | H56: =ROUND(IF(ISNUMBER(D56),D56,C56)+E56+F56+G56,2) -> 19904 | J56: =IF(I56="","",I56-H56) | K56: Not issued
A57: 26.32.13 | B57: Alternate 9 -- Whole-House Generator | C57: =SUM(Estimate!F644) -> 58700 | D57: =ROUND(Estimate!F648,0) -> 68728 | H57: =ROUND(IF(ISNUMBER(D57),D57,C57)+E57+F57+G57,2) -> 68728 | J57: =IF(I57="","",I57-H57) | K57: Not issued
A58: 23.81.46 | B58: Alternate 10 -- Energy-Recovery Ventilator (ERV) | C58: =SUM(Estimate!F654) -> 10000 | D58: =ROUND(Estimate!F658,0) -> 11708 | H58: =ROUND(IF(ISNUMBER(D58),D58,C58)+E58+F58+G58,2) -> 11708 | J58: =IF(I58="","",I58-H58) | K58: Not issued
A59: 26.00.00 | B59: Alternate 11 -- Security System | C59: =SUM(Estimate!F663) -> 12000 | D59: =ROUND(Estimate!F667,0) -> 14050 | H59: =ROUND(IF(ISNUMBER(D59),D59,C59)+E59+F59+G59,2) -> 14050 | J59: =IF(I59="","",I59-H59) | K59: Not issued
A60: 26.00.00 | B60: Alternate 12 -- AV Equipment, Speakers and Wi-Fi | C60: =SUM(Estimate!F674) -> 76000 | D60: =ROUND(Estimate!F678,0) -> 88984 | H60: =ROUND(IF(ISNUMBER(D60),D60,C60)+E60+F60+G60,2) -> 88984 | J60: =IF(I60="","",I60-H60) | K60: Not issued
A61: 05.70.00, 12.24.00 | B61: Alternate 13 -- Interior Shades | C61: =SUM(Estimate!F686) -> 81704 | D61: =ROUND(Estimate!F690,0) -> 95662 | H61: =ROUND(IF(ISNUMBER(D61),D61,C61)+E61+F61+G61,2) -> 95662 | J61: =IF(I61="","",I61-H61) | K61: Not issued
A62: 08.80.00 | B62: Alternate 14 -- Stair Glazing Privacy Film | C62: =SUM(Estimate!F696) -> 10000 | D62: =ROUND(Estimate!F700,0) -> 11708 | H62: =ROUND(IF(ISNUMBER(D62),D62,C62)+E62+F62+G62,2) -> 11708 | J62: =IF(I62="","",I62-H62) | K62: Not issued
A63: 08.50.00 | B63: Alternate -- Laminated Glazing Upgrade (A0.20 Note 03) | C63: =SUM(Estimate!F708) -> 24405 | D63: =ROUND(Estimate!F712,0) -> 28574 | H63: =ROUND(IF(ISNUMBER(D63),D63,C63)+E63+F63+G63,2) -> 28574 | J63: =IF(I63="","",I63-H63) | K63: Not issued
A64: 02.82.00 | B64: Alternate 15 -- Asbestos Testing (If Needed) | C64: =SUM(Estimate!F717) -> 9000 | D64: =ROUND(Estimate!F721,0) -> 10538 | H64: =ROUND(IF(ISNUMBER(D64),D64,C64)+E64+F64+G64,2) -> 10538 | J64: =IF(I64="","",I64-H64) | K64: Not issued
A65: 01.71.23 | B65: Alternate 16 -- Surveying | C65: =SUM(Estimate!F726) -> 9500 | D65: =ROUND(Estimate!F730,0) -> 11123 | H65: =ROUND(IF(ISNUMBER(D65),D65,C65)+E65+F65+G65,2) -> 11123 | J65: =IF(I65="","",I65-H65) | K65: Not issued
A66: 06.15.00 | B66: Alternate 17 -- Deduct -- Cumaru Decking in Lieu of Ipe | C66: =SUM(Estimate!F736) -> -18523.582 | D66: =ROUND(Estimate!F740,0) -> -20175 | H66: =ROUND(IF(ISNUMBER(D66),D66,C66)+E66+F66+G66,2) -> -20175 | J66: =IF(I66="","",I66-H66) | K66: Not issued
A67: 06.15.00 | B67: Alternate 18 -- Deduct -- Red Balau Decking in Lieu of Ipe | C67: =SUM(Estimate!F746) -> -29108.486 | D67: =ROUND(Estimate!F750,0) -> -31704 | H67: =ROUND(IF(ISNUMBER(D67),D67,C67)+E67+F67+G67,2) -> -31704 | J67: =IF(I67="","",I67-H67) | K67: Not issued
A68: 01.74.23 | B68: Alternate 19 -- Final Cleaning at Turnover | C68: =SUM(Estimate!F755) -> 6000 | D68: =ROUND(Estimate!F759,0) -> 7025 | H68: =ROUND(IF(ISNUMBER(D68),D68,C68)+E68+F68+G68,2) -> 7025 | J68: =IF(I68="","",I68-H68) | K68: Not issued
A69: TOTAL -- ALTERNATES ON PROPOSAL | H69: =SUMIFS(H49:H68,I49:I68,"<>") -> 0 | I69: =SUM(I49:I68) -> 0
A70: TOTAL -- PRICED, NOT ON PROPOSAL | H70: =SUMIFS(H49:H68,I49:I68,"") -> 723930
A71: TOTAL -- BASE BID + ALL ALTERNATES | H71: =ROUND(C43+SUM(H49:H68),0) -> 5437846

Sheet Notes & Clarifications
A1: Eun/Yu Residence -- 28 Country Club Lane South -- Notes & Clarifications
A2: Job E26040 | 28 Country Club Lane South, Briarcliff Manor, NY 10510 | BLDG Estimating | 2026-09-23
A4: Type | B4: Item | C4: Clarification
A5: EXCLUSION | B5: Insurance Endorsements Required by MTA | C5: Insurance endorsements, additional insured requirements and any other special insurance coverage required by the MTA are not included.
A6: EXCLUSION | B6: Waterproofing Membrane | C6: Waterproofing membrane and drainage mat at foundation walls 'as required' are not included. Dampproofing per the geotechnical report is included. Waterproofing will be priced separately if required by the engineer. (02/A1.10)
A7: EXCLUSION | B7: Landscaping and Final Grading | C7: Landscaping of all kinds is not included. This covers final grading, topsoil, lawns, softscape, plantings, irrigation, landscape lighting, integrated roof/building planters and the planter/trellis under the garage overhang, pending the landscape architect. (SUPP Sec. 8.1)
A8: EXCLUSION | B8: Finished Basement | C8: Phase II finished basement construction is not included and will be filed under a separate permit. Phase 1 unfinished scope is included. (SUPP Sec. 2, 8.3; A1.10)
A9: EXCLUSION | B9: Upper Roof Deck Finishes and Hot Tub | C9: Upper roof deck finishes and hot tub are deferred and priced only as Alternate 5. (SUPP Sec. 8.4)
A10: EXCLUSION | B10: Built-In Planter Assemblies | C10: Built-in planter assemblies at decks and roof deck are not included. (A0.10, A1.13, SUPP Sec. 5)
A11: EXCLUSION | B11: Infiltration System Inspection | C11: Design engineer site inspection 72 hours prior to backfilling the infiltration system is not included. (C-2 Boxed Note)
A12: EXCLUSION | B12: Terrace Drains | C12: Terrace drains as required are not included. (SUPP Sec. 6.8)
A13: EXCLUSION | B13: Temporary Excavation Support | C13: Temporary excavation support (trench boxes, sheeting and shoring) designed by a NYS licensed P.E. is not included. (GEO p.16-17, Table 8)
A14: EXCLUSION | B14: Dewatering | C14: Dewatering, if needed, including sumps, pumps, discharge piping and any related treatment or discharge permits, is not included. (GEO p.4, p.16-17; Narrative p.14)
A15: EXCLUSION | B15: Excess Cut and Imported Soil | C15: Off-site removal and legal disposal of excess cut, and certified clean imported soil, are not included. (C-3 Site Notes 7-8)
... A59: CLARIFICATION | B59: Appliance Vendor Scope | C59: The appliance vendor proposal (Albano) covers delivery and uncrating only. Installation, panels and handles on panel-ready units, and old appliance disposal are by others. (PROP Appliances)

Sheet General Requirements
A1: Eun/Yu Residence · 28 Country Club Lane South · E26040
A2: General Requirements, Division 01 · Montana Contracting · Draft, September 30, 2026
A3: Legend: blue text is an input you can change. Yellow fill marks the assumptions to confirm first. Black text is a formula. Every total follows the inputs.
A5: INPUTS
B6: Duration Carried, Weeks | E6: 48 | G6: Ten to eleven months on site, plus float for winter foundations and the factory slot (E26040 duration note, 9/30/2026).
B7: Duration Carried, Months | E7: =E6*12/52 -> 11.076923 | G7: Formula.
B8: Superintendent Base Salary, $ per Year | E8: 135000 | G8: Salary.com, Construction Superintendent, New York NY, as of 9/1/2026: median $133,318, 25th to 75th percentile $119,481 to $150,132. Replace with Montana payroll.
B9: Project Manager Base Salary, $ per Year | E9: 135000 | G9: Salary.com, Project Manager - Construction, New York NY, as of 9/1/2026: median $136,606, 25th to 75th percentile $126,075 to $150,074. Replace with Montana payroll.
B10: Payroll Burden, % of Salary | E10: 0.32 | G10: Assumption: FICA, NY unemployment, workers comp, disability and paid family leave, health and retirement. Replace with Montana burden.
B11: Superintendent Time | E11: 1 | G11: Full time (Matt, 9/30/2026).
B12: Project Manager Time | E12: 0.5 | G12: Half time (Matt, 9/30/2026).
B13: Laborer, Loaded $ per Hour | E13: 52 | G13: Budget rate, Westchester open shop, 09/2026. Assumption.
B14: Laborer, Hours per Week | E14: 8 | G14: One day a week for cleanup, protection and deliveries.
B15: Direct Cost of the Work, $ | E15: 4134000 | G15: Direct total in the presentation: estimate v10 trades rounded to $1,000. The v10 subtotal is $4,132,394. Placeholder until the final estimate.
B16: General Conditions Rate, % of Direct | E16: =Estimate!E516 -> 0.075 | G16: Linked to the base bid General Conditions rate (Estimate E517). Deduct alternates 17 and 18 carry 0%.
A18: CSI | B18: Item | C18: Qty | D18: Unit | E18: Rate ($) | F18: Total ($) | G18: Basis
A19: 01 31 00 | B19: Project Management and Coordination
A20: 01 31 13 | B20: Superintendent, Full Time | C20: =$E$6*$E$11 -> 48 | D20: wk | E20: 2650 | F20: =ROUND(C20*E20,0) -> 127200 | G20: Base salary plus burden, per week. On site every working day from mobilization to the punch list and turnover.
A21: 01 31 13 | B21: Project Manager, Half Time | C21: =$E$6*$E$12 -> 24 | D21: wk | E21: 2650 | F21: =ROUND(C21*E21,0) -> 63600 | G21: Buyout, submittals, schedule, Signature and Res4 coordination, billing, closeout, O&M manuals and warranties.
B22: Principle & GS Oversight (20% Oversight) | C22: =C20*0.2 -> 9.6 | D22: wk | E22: 3650 | F22: =ROUND(C22*E22,0) -> 35040
A23: 01 31 13 | B23: Superintendent Truck, Fuel, Tolls and Phone | C23: =$E$7 -> 11.076923 | D23: mo | E23: 1200 | F23: =ROUND(C23*E23,0) -> 13292 | G23: Truck allocation, fuel, tolls, phone and tablet.
A24: 01 31 19 | B24: Project Manager Site Visits and Factory Trips to Moosic, PA | C24: 1 | D24: LS | E24: 2500 | F24: =ROUND(C24*E24,0) -> 2500 | G24: Mileage and tolls. Three factory visits: before production, during production and before shipping.
B25: Subtotal, Project Management and Coordination | F25: =SUM(F20:F24) -> 241632
A27: 01 50 00 | B27: Temporary Facilities and Controls
A28: 01 52 13 | B28: Storage Container, 20 ft, Locked | C28: =$E$7 -> 11.076923 | D28: mo | E28: 225 | F28: =ROUND(C28*E28,0) -> 2492 | G28: Field storage. No office trailer. The superintendent runs the job from the truck, and from the basement after the set.
A29: 01 52 13 | B29: Storage Container Delivery and Pickup | C29: 1 | D29: LS | E29: 600 | F29: =ROUND(C29*E29,0) -> 600 | G29: One delivery, one pickup.
A30: 01 52 19 | B30: Portable Toilet with Weekly Service | C30: =$E$7 -> 11.076923 | D30: mo | E30: 275 | F30: =ROUND(C30*E30,0) -> 3046 | G30: Zters 2026 guide: $125 to $275 a month with weekly service. Carried at the top of the range.
A31: 01 51 36 | B31: Temporary Water | C31: 1 | D31: LS | E31: 1500 | F31: =ROUND(C31*E31,0) -> 1500 | G31: Tap and hose bibb with backflow at the existing service. Temporary power is carried in Electrical.
A32: 01 51 23 | B32: Winter Protection at Foundations, January to March | C32: 1 | D32: LS | E32: 0 | F32: =ROUND(C32*E32,0) -> 0 | G32: Ground-thaw heater and fuel, insulated blankets and tenting at footings and walls, hot water and accelerator on winter pours. Not in estimate v10. It backs the presentation line that cold-weather protection is in the base price.
A33: 01 56 00 | B33: Snow Removal and Site Access, January to March | C33: 1 | D33: LS | E33: 0 | F33: =ROUND(C33*E33,0) -> 0 | G33: Plowing the entrance and staging area for deliveries and concrete trucks.
A34: 01 56 39 | B34: Protection of Finished Work | C34: 1 | D34: LS | E34: 4500 | F34: =ROUND(C34*E34,0) -> 4500 | G34: Ram Board over the white oak and tile, stair tread covers, counter, glass and corner protection, one re-protect before turnover.
A35: 01 35 23 | B35: Site Safety | C35: 1 | D35: LS | E35: 4000 | F35: =ROUND(C35*E35,0) -> 4000 | G35: Fall protection at the flat roofs and parapets, fire extinguishers, first aid, signage and the site safety plan.
B36: Subtotal, Temporary Facilities and Controls | F36: =SUM(F28:F35) -> 16138
A38: 01 71 00 | B38: Field Engineering
A39: 01 71 23 | B39: Survey: Stakeout, Foundation Location Survey and Final As-Built | C39: 1 | D39: LS | F39: =ROUND(C39*E39,0) -> 0 | G39: Licensed surveyor. Includes the certified stormwater as-built required before the C.O. (C-3 Site Note 10), if it is ours. Estimate v10 lists it to confirm.
B40: Subtotal, Field Engineering | F40: =SUM(F39:F39) -> 0
A42: 01 74 00 | B42: Cleaning and Waste Management
A43: 01 74 19 | B43: Dumpster Hauls, 30 Yard | C43: 12 | D43: EA | E43: 950 | F43: =ROUND(C43*E43,0) -> 11400 | G43: About one a month. Central container for all trades, per the estimate clarifications. $875 carries a 30-yard haul with tonnage, above the $300 to $800 NY range by size (Mr. Cheapee, 11/2025). Existing-house demolition is in Alternate 1. Excess cut is in Earthwork.
A44: 01 74 13 | B44: Laborer for Cleanup, Protection and Deliveries | C44: =$E$6*$E$14 -> 384 | D44: hr | E44: 45 | F44: =ROUND(C44*E44,0) -> 17280 | G44: One day a week for the duration.
A45: 01 74 23 | B45: Final Cleaning at Turnover | C45: 0 | D45: LS | E45: 6000 | F45: =ROUND(C45*E45,0) -> 0 | G45: Moved to Alternate 19 (Final Cleaning at Turnover, $6,000). Not carried in the base.
B46: Subtotal, Cleaning and Waste Management | F46: =SUM(F43:F45) -> 28680
B48: Total General Requirements | F48: =F25+F36+F40+F46 -> 286450
A50: CHECKS
B51: Average per Month | F51: =F48/$E$7 -> 25860.069
B52: Percent of Direct Cost | F52: =F48/$E$15 -> 0.069291243 | G52: The rate to enter for General Conditions if the estimate keeps it as a percentage.
B53: =TEXT($E$16,"0.0%")&" General Conditions Carried in the Estimate" -> 7.5% General Conditions Carried in the Estimate | F53: =$E$15*$E$16 -> 310050
B54: Over (Under) the Carried Rate | F54: =F48-$E$15*$E$16 -> -23600
B55: Cost of Each Added Month | F55: =(E20*$E$11+E21*$E$12+E44*$E$14)*52/12+E23+E28+E30 -> 20485 | G55: Staff, laborer, truck, container and toilet. Every other line is a lump sum.
A57: CARRIED ELSEWHERE IN ESTIMATE v10
B58: Temporary Power and Lighting | G58: Electrical, 26.05.19, 12 months, $9,000.
B59: Set Day: Crane Pad, Stone Access, Road Plates, Police Detail and Road Closure Permit | G59: Modular, 13.42.00, site preparation for delivery and setting, $14,500.
B60: Crane, Rigging, Set Crew, Temporary Bracing and Roof Protection | G60: Modular, 13.42.00, Tony Stein proposal, $19,660.
B61: Factory Freight, Third-Party Inspections and NY Seals | G61: Modular, 13.42.00, per the Signature estimate of 8/14/2026.
B62: HERS Rater Before Production | G62: Modular, 13.42.00, $3,500.
B63: Erosion Control Inspections, Stabilized Entrance, Road Sweeping and Dust Control | G63: Site Clearing and Erosion Control, 31.25.00. Sweeping and dust control run 12 months.
B64: Project Limiting Fence and Tree Protection | G64: Site Clearing and Erosion Control, 31.25.00 and 31.10.00.
B65: Protection of Adjoining Property and Stone Walls, with the Pre-Construction Photo Survey | G65: Demolition, 02.41.16.
B66: Excavation Support and Dewatering (Excluded, Not Carried) | G66: Excluded in the estimate notes. Priced only if required.
B67: Trade Permits, Trade Testing and Cleanup into the GC Container | G67: Every subcontractor, per the estimate clarifications.
B68: Principal Oversight | G68: In the fee.
B69: General Liability Insurance | G69: In the Insurance markup.
A71: BY OWNER OR NOT CARRIED · CONFIRM IN THE PROPOSAL
B72: Building Permit and Municipal Fees | G72: Assumed by Owner.
B73: Full-Time Geotechnical Inspection and Testing | G73: The Carlin-Simpson report has the Owner retain the geotechnical engineer (estimate v10 clarification).
B74: Special Inspections Beyond Trade Testing | G74: Assumed by Owner.
B75: Builder's Risk Insurance | G75: Assumed by Owner.
B76: Temporary Heat Inside the House | G76: Not carried. The schedule finishes in October or November with the geothermal system running.
B77: Pre-Construction Services | G77: Optional, priced separately.
A79: SOURCES
B80: Salary.com, Construction Superintendent Salary in New York, NY (as of 9/1/2026): https://www.salary.com/research/salary/listing/construction-superintendent-salary/new-york-ny
B81: Salary.com, Project Manager - Construction Salary in New York, NY (as of 9/1/2026): https://www.salary.com/research/salary/benchmark/project-manager-construction-salary/new-york-ny
B82: Zters, How Much Does It Cost to Rent a Porta Potty? (2026): https://www.zters.com/blog/explained-how-much-does-it-cost-to-rent-a-porta-potty
B83: Mr. Cheapee, dumpster rental cost in NY, $300 to $800 by size (11/2025): https://mrcheapeeinc.com/2025/11/28/how-much-does-a-dumpster-rental-cost-in-ny/
B84: E26040 estimate report v10 (9/23/2026), Res4 Supplemental Project Information (9/1/2026), Signature estimate (8/14/2026), Tony Stein erection proposal.

Sheet Electrical Pricing Basis
A1: Eun/Yu Residence -- Electrical, Solar/Battery/Generator and Shades -- Pricing Basis (2026-09-28)
A2: Raw cost only (no GC OH&P). Furnish and install broken out. Quantities are conceptual counts from A0.20, A0.11 and A1.20-A1.33; confirm with the electrical and shade subs. Totals link to the Estimate sheet.
A4: Est. Row | B4: CSI | C4: Scope Item | D4: Qty | E4: Unit | F4: Furnish / Unit | G4: Install / Unit | H4: Furnish Total | I4: Install Total | J4: Line Total | K4: Basis
A5: BASE BID -- ELECTRICAL (26)
A6: 364 | B6: 26.05.19 | C6: Provide Temporary Power And Lighting [Not Specified] (Site) | D6: =Estimate!C391 -> 1 | E6: LS | F6: 4500 | G6: 7500 | H6: =D6*F6 -> 4500 | I6: =D6*G6 -> 7500 | J6: =H6+I6 -> 12000 | K6: Temp service pole, meter pan, 100A temp panel, GFCI cords, string lighting in modules/basement; ~10-12 mo. Utility fees excluded.
A7: 365 | B7: 26.05.19 | C7: Connect Wiring Between Modules [12/2 ROMEX WIRING (ALL IN MODULES BY FACTORY. CONNECTIONS BETWEEN MODULES BY GC.)] (House) | D7: =Estimate!C393 -> 60 | E7: EA | F7: 15 | G7: 95 | H7: =D7*F7 -> 900 | I7: =D7*G7 -> 5700 | J7: =H7+I7 -> 6600 | K7: Mate-line splices between modules, ~60 connections (6 modules, 2 floors) in accessible J-boxes, labeled.
A8: 366 | B8: 26.05.19 | C8: Provide All Rough Electrical Wiring Outside Modules (Basement, Garage, Exterior, Stair Volume, Decks, Roof Deck) [Not Specified] (House) | D8: =Estimate!C394 -> 30 | E8: EA | F8: 150 | G8: 300 | H8: =D8*F8 -> 4500 | I8: =D8*G8 -> 9000 | J8: =H8+I8 -> 13500 | K8: ~30 branch circuits outside modules (basement, garage, stair volume, exterior soffits, decks, roof deck). Covers wire/boxes for F/O-I/O fixture rows. Blue F/I device rows already carry their own wiring.
A9: 367 | B9: 26.05.19 | C9: Provide Code-Required Convenience Outlets And Equipment Circuits In Unfinished Basement [CONVENIENCE OUTLETS IN UNFINISHED BASEMENT IN PHASE 1 SCOPE.] (House) | D9: =Estimate!C395 -> 1 | E9: LS | F9: 2300 | G9: 5200 | H9: =D9*F9 -> 2300 | I9: =D9*G9 -> 5200 | J9: =H9+I9 -> 7500 | K9: Phase 1 basement: ~8 convenience outlets + equipment circuits for 2 geo heat pumps, flow center, circulators, AHU #1, 2 tankless heaters, sump/misc.
A10: 370 | B10: 26.05.19 | C10: Connect Factory Solar Conduit Between Modules To Load Center And Roof [(2X) 2" PVC CONDUIT] (House) | D10: =Estimate!C398 -> 1 | E10: LS | F10: 600 | G10: 1900 | H10: =D10*F10 -> 600 | I10: =D10*G10 -> 1900 | J10: =H10+I10 -> 2500 | K10: Connect (2) 2in factory solar conduits across mate lines, extend to basement load center and roof penetration; pull string. PVC vs EMT conflict open (Review #26).
A11: 372 | B11: 26.09.23 | C11: Replace Factory Temporary Rocker Switches With Ship-Loose RadioRA3 Controls [LUTRON RADIORA3] (House) | D11: =Estimate!C400 -> 65 | E11: EA | F11: 0 | G11: 55 | H11: =D11*F11 -> 0 | I11: =D11*G11 -> 3575 | J11: =H11+I11 -> 3575 | K11: I/O: swap factory temporary rockers for ship-loose RadioRA3 controls in modules. ~21 keypads + ~44 dimmers/switches (A1.21, A1.22 keypad tags).
A12: 373 | B12: 26.09.23 | C12: F/I All Wireless Devices, Processor And Repeaters [RADIORA 3 ALL IN ONE PROCESSOR; RADIORA 3 REPEATER] (House) | D12: =Estimate!C401 -> 1 | E12: LS | F12: 0 | G12: 800 | H12: =D12*F12 -> 0 | I12: =D12*G12 -> 800 | J12: =H12+I12 -> 800 | K12: I/O per Steve 9/28: factory supplies. Receive/inventory ($300) + mount/connect processor and ~3 repeaters (4 @ $125). Device install is on rows 372/374; programming on row 378.
A13: 375 | B13: 26.09.23 | C13: F/I Remote Dimmer Bank In Basement Utility Closet; Connect And Label Factory Whips [LUTRON SUNNATA DIMMER SWITCH REMOTED IN BASEMENT] (House) | D13: =Estimate!C403 -> 12 | E13: EA | F13: 225 | G13: 95 | H13: =D13*F13 -> 2700 | I13: =D13*G13 -> 1140 | J13: =H13+I13 -> 3840 | K13: Remote Sunnata dimmer bank in basement utility closet (~12 per A1.20): dimmer + multi-gang box; connect and label factory whips.
A14: 376 | B14: 26.09.23 | C14: F/I Pico Switches For Shades In Guest Bath Faceplates [PICO SWITCH BY GC FOR SHADES] (House) | D14: =Estimate!C404 -> 3 | E14: EA | F14: 85 | G14: 35 | H14: =D14*F14 -> 255 | I14: =D14*G14 -> 105 | J14: =H14+I14 -> 360 | K14: Pico + wallplate bracket in guest bath 4-gang plates (A1.22 PIC tags, 3 baths).
A15: 378 | B15: 26.09.23 | C15: Provide All System Programming Including Keypad Engraving And 30-Minute Exhaust Fan Timers [SUGGESTED KEYPAD BUTTON SCHEDULE] (House) | D15: =Estimate!C406 -> 1 | E15: LS | F15: 0 | G15: 8250 | H15: =D15*F15 -> 0 | I15: =D15*G15 -> 8250 | J15: =H15+I15 -> 8250 | K15: Lutron Designer programming ~122 devices @ $55, keypad engraving ~25 @ $45, 30-min fan timers, owner training $400. Shade programming carried in Alt 13.
A16: 379 | B16: 26.09.23 | C16: Provide Compatible Drivers, Dimmers And Lutron Minimum Load Capacitors As Required [Not Specified] (House) | D16: =Estimate!C407 -> 1 | E16: LS | F16: 1000 | G16: 500 | H16: =D16*F16 -> 1000 | I16: =D16*G16 -> 500 | J16: =H16+I16 -> 1500 | K16: Allowance: Lutron LUT-MLC capacitors and compatible dimmers/drivers where fixture loads are low (Lighting Note 10).
A17: 380 | B17: 26.21.00 | C17: Provide Underground Electric Service Including Reconnection / Extension Of Existing Service; Confirm Service Size Adequate [Not Specified] (Site) | D17: =Estimate!C408 -> 1 | E17: LS | F17: 6500 | G17: 7000 | H17: =D17*F17 -> 6500 | I17: =D17*G17 -> 7000 | J17: =H17+I17 -> 13500 | K17: UG service lateral ~150 LF (conductors + 3in PVC), 320A/400A meter-main + grounding. Trenching carried in earthwork (row 349). Utility charges excluded. 200A house panel + 200A EV subpanel likely needs 320A service.
A18: 381 | B18: 26.21.00 | C18: F/I Underground Conduit For Telephone, Cable And Internet Services [Not Specified] (Site) | D18: =Estimate!C409 -> 300 | E18: LF | F18: 6 | G18: 7 | H18: =D18*F18 -> 1800 | I18: =D18*G18 -> 2100 | J18: =H18+I18 -> 3900 | K18: (2) 2in PVC comm conduits ~150 LF each w/ pull string + pull boxes. Trench by earthwork.
A19: 382 | B19: 26.24.16 | C19: I/O Factory-Supplied 200A Panel Dropped To Basement And Connect Labeled Module Wiring To Panel [ELECTRICAL PANEL & SUBPANEL(S) AS REQ'D.] (House) | D19: =Estimate!C410 -> 1 | E19: LS | F19: 300 | G19: 2100 | H19: =D19*F19 -> 300 | I19: =D19*G19 -> 2100 | J19: =H19+I19 -> 2400 | K19: I/O factory 200A panel: set in basement, terminate ~40 labeled module circuits, bond/ground.
A20: 384 | B20: 26.27.26 | C20: I/O Factory-Supplied Faceplates In Modules And F/I Faceplates Outside Modules [LUTRON CLARO SCREWLESS DESIGNER SERIES, WHITE] (House) | D20: =Estimate!C412 -> 1 | E20: LS | F20: 700 | G20: 800 | H20: =D20*F20 -> 700 | I20: =D20*G20 -> 800 | J20: =H20+I20 -> 1500 | K20: Install ~150 factory Claro plates in modules; F/I ~60 Claro plates outside modules not already in device rates.
A21: 387 | B21: 26.27.26 | C21: F/I Outlet In Underside Of Medicine Cabinet With Stainless Steel Faceplate (Roughing By Factory) [Not Specified] (House) | D21: =Estimate!C416 -> 2 | E21: EA | F21: 60 | G21: 115 | H21: =D21*F21 -> 120 | I21: =D21*G21 -> 230 | J21: =H21+I21 -> 350 | K21: Outlet under Robern medicine cabinets, primary bath (L+R), SS plate; factory rough.
A22: 388 | B22: 26.27.26 | C22: Provide Black Devices On Black Steel Walls [ALL DEVICES ON BLACK STEEL WALLS TO BE BLACK.] (House) | D22: =Estimate!C417 -> 10 | E22: EA | F22: 25 | G22: 10 | H22: =D22*F22 -> 250 | I22: =D22*G22 -> 100 | J22: =H22+I22 -> 350 | K22: Black device/plate upcharge at black steel walls (~10 devices).
A23: 389 | B23: 26.51.13 | C23: F/O L1 And L2 Downlights Outside Modules (Stair Volume, Basement Stair) [JUNO IC1LED-G4-09LM-30K-90CRI; JUNO 2LEDTRIM-G2-DC-30K-90CRI-FL] (House) | D23: =Estimate!C418 -> 10 | E23: EA | F23: 140 | G23: 0 | H23: =D23*F23 -> 1400 | I23: =D23*G23 -> 0 | J23: =H23+I23 -> 1400 | K23: F/O Juno IC1LED 4in / 2LEDTRIM 2in outside modules: ~3 basement stair + ~7 stair volume/landings.
A24: 390 | B24: 26.51.13 | C24: I/O L1 And L2 Downlights Outside Modules [Not Specified] (House) | D24: =Estimate!C419 -> 10 | E24: EA | F24: 0 | G24: 165 | H24: =D24*F24 -> 0 | I24: =D24*G24 -> 1650 | J24: =H24+I24 -> 1650 | K24: I/O L1/L2 outside modules incl. housing set, trim, connect.
A25: 394 | B25: 26.51.13 | C25: F/O L8 Linear Ceiling Lights Flush Into Cedar Ceilings, Lengths Confirmed By GC [WAC INVISILED PRO2+ LED-TC24-30-90-X-WT ANGLED RECESSED CHANNEL, WITH FROSTED DIFFUSER] (House) | D25: =Estimate!C423 -> 80 | E25: LF | F25: 60 | G25: 0 | H25: =D25*F25 -> 4800 | I25: =D25*G25 -> 0 | J25: =H25+I25 -> 4800 | K25: F/O WAC InvisiLED Pro2+ tape + angled recessed channel + frosted diffuser, ~80 LF in cedar ceilings (lengths TBC by GC). Drivers on row 407.
A26: 395 | B26: 26.51.13 | C26: I/O L8 Linear Ceiling Lights [Not Specified] (House) | D26: =Estimate!C424 -> 80 | E26: LF | F26: 0 | G26: 38 | H26: =D26*F26 -> 0 | I26: =D26*G26 -> 3040 | J26: =H26+I26 -> 3040 | K26: I/O L8 flush in cedar: channel set/coordination with carpenter, tape, diffuser, connect.
A27: 398 | B27: 26.51.13 | C27: I/O Factory-Supplied L12BB Step Lights On Black Steel Wall After Steel Install [WAC WL-LED200-C-BK BLACK] (House) | D27: =Estimate!C427 -> 3 | E27: EA | F27: 0 | G27: 125 | H27: =D27*F27 -> 0 | I27: =D27*G27 -> 375 | J27: =H27+I27 -> 375 | K27: I/O factory-supplied L12BB black step lights on black steel wall after steel install.
A28: 399 | B28: 26.51.13 | C28: F/O L19 Bedside Reading Lamps (Guest) With Integral Switch [TBD] (House) | D28: =Estimate!C428 -> 6 | E28: EA | F28: 200 | G28: 0 | H28: =D28*F28 -> 1200 | I28: =D28*G28 -> 0 | J28: =H28+I28 -> 1200 | K28: Owner allowance $200/EA (SUPP 6.11); 2 per guest bedroom x 3.
A29: 400 | B29: 26.51.13 | C29: I/O L19 Bedside Reading Lamps [Not Specified] (House) | D29: =Estimate!C429 -> 6 | E29: EA | F29: 0 | G29: 125 | H29: =D29*F29 -> 0 | I29: =D29*G29 -> 750 | J29: =H29+I29 -> 750 | K29: I/O L19 bedside lamps w/ integral switch.
A30: 401 | B30: 26.51.13 | C30: F/O L20 Dining Pendants [TBD] (House) | D30: =Estimate!C430 -> 5 | E30: EA | F30: 400 | G30: 0 | H30: =D30*F30 -> 2000 | I30: =D30*G30 -> 0 | J30: =H30+I30 -> 2000 | K30: Owner allowance $400/EA (SUPP 6.11); I/O already priced row 402.
A31: 403 | B31: 26.51.13 | C31: F/O L21 Primary Bedroom Pendants [TBD] (House) | D31: =Estimate!C432 -> 2 | E31: EA | F31: 400 | G31: 0 | H31: =D31*F31 -> 800 | I31: =D31*G31 -> 0 | J31: =H31+I31 -> 800 | K31: Owner allowance $400/EA (SUPP 6.11); 2 per A1.22.
A32: 404 | B32: 26.51.13 | C32: I/O L21 Primary Bedroom Pendants [Not Specified] (House) | D32: =Estimate!C433 -> 2 | E32: EA | F32: 0 | G32: 300 | H32: =D32*F32 -> 0 | I32: =D32*G32 -> 600 | J32: =H32+I32 -> 600 | K32: I/O L21 primary bedroom pendants.
A33: 405 | B33: 26.51.13 | C33: I/O Factory-Supplied Lights In Foyer Millwork Sleeve [SPEC'D LIGHTS IN SLEEVE SHIPPED LOOSE BY FACTORY, INSTALLED BY GC] (House) | D33: =Estimate!C434 -> 1 | E33: LS | F33: 0 | G33: 500 | H33: =D33*F33 -> 0 | I33: =D33*G33 -> 500 | J33: =H33+I33 -> 500 | K33: I/O factory-supplied lights in foyer millwork sleeve (~4).
A34: 406 | B34: 26.51.13 | C34: F/I All Light Bulbs [ALL LIGHT BULBS TO BE PROVIDED BY GC.] (House) | D34: =Estimate!C435 -> 1 | E34: LS | F34: 600 | G34: 0 | H34: =D34*F34 -> 600 | I34: =D34*G34 -> 0 | J34: =H34+I34 -> 600 | K34: Bulbs for pendants, lamps, misc. non-integral fixtures (most fixtures are integral LED).
A35: 407 | B35: 26.51.13 | C35: F/I Remote Transformers For Lighting, Accessible, Locations Coordinated In Field [Not Specified] (House) | D35: =Estimate!C436 -> 12 | E35: EA | F35: 150 | G35: 75 | H35: =D35*F35 -> 1800 | I35: =D35*G35 -> 900 | J35: =H35+I35 -> 2700 | K35: Lutron-compatible remote drivers for L6A, L8, step lights; accessible locations.
A36: 409 | B36: 26.56.00 | C36: I/O L4 Exterior Downlights [Not Specified] (House) | D36: =Estimate!C438 -> 38 | E36: EA | F36: 0 | G36: 175 | H36: =D36*F36 -> 0 | I36: =D36*G36 -> 6650 | J36: =H36+I36 -> 6650 | K36: I/O Juno MD1 exterior downlights in stucco/soffits, wet-location connect.
C37: Subtotal -- Base Bid -- Electrical (26) | H37: =SUM(H6:H36) -> 39025 | I37: =SUM(I6:I36) -> 70465 | J37: =SUM(J6:J36) -> 109490
A39: ALTERNATES -- ELECTRICAL
A40: 509 | B40: 26.05.19 | C40: [Electrical] Provide Disconnect And Safe-Off Of Existing Dwelling Electrical Service Prior To Demolition [Not Specified] | D40: =Estimate!C535 -> 1 | E40: LS | F40: 0 | G40: 1500 | H40: =D40*F40 -> 0 | I40: =D40*G40 -> 1500 | J40: =H40+I40 -> 1500 | K40: Alt 1: utility disconnect coordination, safe-off and make-safe existing house service before demo.
A41: 556 | B41: 26.05.19 | C41: [Electrical] Provide Future GFI Hot Tub Circuit Provision At Roof Deck [FUTURE GFI HOT TUB] | D41: =Estimate!C585 -> 1 | E41: LS | F41: 900 | G41: 1300 | H41: =D41*F41 -> 900 | I41: =D41*G41 -> 1300 | J41: =H41+I41 -> 2200 | K41: Alt 5: 60A GFCI spa disconnect + ~80 LF circuit to roof deck, capped for future hot tub.
A42: 577 | B42: 26.31.00 | C42: [Solar, Battery & Generator] F/I Rooftop Solar Panels And Associated Equipment, Fully Ballasted For Flat Roofs [PANEL CLAW POLAR BEAR III OR EQUAL] | D42: =Estimate!C608 -> 1 | E42: LS | F42: 12360 | G42: 11490 | H42: =D42*F42 -> 12360 | I42: =D42*G42 -> 11490 | J42: =H42+I42 -> 23850 | K42: Alt 7: ~8.4 kW (20 x 420W panels, ~440 SF) ballasted, microinverters, combiner, disconnect, interconnection, design/permit. Matches 9/28 solar number ($13,000 array + $10,850 electrical). Federal 25D credit expired 12/31/2025.
A43: 586 | B43: 26.33.00 | C43: [Solar, Battery & Generator] F/I Solar Battery Backup System [Not Specified] | D43: =Estimate!C623 -> 1 | E43: LS | F43: 12500 | G43: 4500 | H43: =D43*F43 -> 12500 | I43: =D43*G43 -> 4500 | J43: =H43+I43 -> 17000 | K43: Alt 8: one 13.5 kWh battery with integrated inverter/gateway, backup-loads panel, install, commissioning. Confirm platform matches solar (microinverter vs string).
A44: 595 | B44: 26.32.13 | C44: [Solar, Battery & Generator] F/I Whole-House Generator [Not Specified] | D44: =Estimate!C635 -> 1 | E44: LS | F44: 11500 | G44: 7000 | H44: =D44*F44 -> 11500 | I44: =D44*G44 -> 7000 | J44: =H44+I44 -> 18500 | K44: Alt 9: 24-26 kW air-cooled standby gen, 400A service-rated ATS, pad, electrical install, startup/permit. Gas piping by plumbing.
C45: Subtotal -- Alternates -- Electrical | H45: =SUM(H40:H44) -> 37260 | I45: =SUM(I40:I44) -> 25790 | J45: =SUM(J40:J44) -> 63050
A47: ALTERNATE 13 -- INTERIOR SHADES
A48: 633 | B48: 05.70.00 | C48: [Decorative Metal & Railings] F/I Removable Custom Steel Valance At Roller Shades With Recessed Magnets Epoxied Into Head Trim [1/8" THK. STEEL PLATE WELDED TO 1-1/2" X 1-1/2" X 1/8" STEEL ANGLE, POWDER COATED WHITE; 1/2" DIA. X 3/8" THK. NEODYMIUM RARE EARTH DISC MAGNET N42 (PART NO. D86) FROM KJMAGNETICS.COM] | D48: =Estimate!C682 -> 150 | E48: LF | F48: 95 | G48: 35 | H48: =D48*F48 -> 14250 | I48: =D48*G48 -> 5250 | J48: =H48+I48 -> 19500 | K48: Alt 13: ~145 LF of shade heads (24 openings). 1/8in plate on 1-1/2 angle, white powder coat, epoxied N42 magnets.
A49: 634 | B49: 12.24.00 | C49: [Window Treatments] F/I Battery-Powered Roller Shades Within Window Trim In White Architectural Fascia At Scheduled Locations [LUTRON BATTERY-POWERED ROLLER SHADES - SIVOIA QS TRIATHLON - CONTROLLED ON RADIORA SYSTEM] | D49: =Estimate!C683 -> 24 | E49: EA | F49: 1446 | G49: 175 | H49: =D49*F49 -> 34704 | I49: =D49*G49 -> 4200 | J49: =H49+I49 -> 38904 | K49: Alt 13: 24 Sivoia QS Triathlon battery shades, 20 openings (wide doors 115/120/224 split in 2). 2 small @ $850, 11 med @ $1,250, 11 large @ $1,750 furnish incl. fascia/jamb mount.
A50: 635 | B50: 12.24.00 | C50: [Window Treatments] F/I Primary Bedroom Blackout Shades And Ceiling-Mounted Shades At Windows / Doors 214, 215, 216 [LUTRON SIVOIA QS TRIATHLON SHADES W/ BLACKOUT FABRIC & LUTRON PALLADIOM BATTERY-POWERED CLG-MTD SHADES] | D50: =Estimate!C684 -> 8 | E50: EA | F50: 2400 | G50: 200 | H50: =D50*F50 -> 19200 | I50: =D50*G50 -> 1600 | J50: =H50+I50 -> 20800 | K50: Alt 13: primary bed 214/215/216 = 4 Triathlon blackout (2 med @ $1,350, 2 large @ $1,850) + 4 Palladiom battery ceiling shades @ $3,200.
A51: 636 | B51: 12.24.00 | C51: [Window Treatments] Provide Mock-Up Of Roller Shade And Custom Valance Assembly [GC TO PREPARE MOCK-UP OF ROLLER SHADE & CUSTOM VALANCE ASSEMBLY] | D51: =Estimate!C685 -> 1 | E51: LS | F51: 1200 | G51: 1300 | H51: =D51*F51 -> 1200 | I51: =D51*G51 -> 1300 | J51: =H51+I51 -> 2500 | K51: Alt 13: one shade + valance mock-up at a typical window, then removal/reuse.
C52: Subtotal -- Alternate 13 -- Interior Shades | H52: =SUM(H48:H51) -> 69354 | I52: =SUM(I48:I51) -> 12350 | J52: =SUM(J48:J51) -> 81704
C54: Base electrical trade total (all rows 364-416 incl. previously priced blue/amber lines) | J54: =Estimate!F446 -> 230950

Sheet Estimate Review
A1: Eun/Yu Residence -- 28 Country Club Lane South -- Estimate Review (Internal)
A2: Job E26040 | 28 Country Club Lane South, Briarcliff Manor, NY 10510 | BLDG Estimating | 2026-09-23
A3: Internal only. Items found reconciling the estimate, the cost detail and the issued proposal. Do not send.
A5: No. | B5: Priority | C5: Area | D5: Finding | E5: Direct $ at Stake | F5: Action Before Issue
A6: 1 | B6: HIGH | C6: Takeoff Mapping | D6: Takeoff lines mapped by meaning: 85 SOW lines priced from NOVATerra (blue), 12 SOW lines covered by an adjacent priced line (INCL), 6 added lines with no SOW match (amber). Concrete rows 70, 72, 73 are REPLACED by the drawing takeoff (green, see next finding). Component detail for every priced line is on the hidden Quantity Basis sheet. | E6: 1519144.9 | F6: Spot-check the Quantity Basis sheet before issue.
A7: 2 | B7: HIGH | C7: Concrete Repriced | D7: NOVATerra rows 70 (pile cap, 1 EA $1,122), 72 (footings, 1 EA $23,678) and 73 (foundation walls, 1 EA $240,040) totaled $264,840.20 with no measurable quantity and no slabs. Replaced by the drawing takeoff: 3658.7 CY at $600/CY base adjusted per line (stairs +100%, pile caps +25%, footings -10%, etc.) = $155,318.73, a $109,521.47 reduction. Adds basement, garage and terrace slabs, terrace stairs, stair frost footings and 12 post footings that NOVATerra missed. Retaining walls sit on Hardscape 32 32 00 and stairs on 32 14 00. | E7: 109521.47 | F7: Send the CY-by-element list to the concrete sub. Footing sizes, pile cap depth and rebar are assumed (no structural drawings); re-run when S-drawings issue.
A8: 3 | B8: MED | C8: Concrete Accessories Priced | D8: Priced at Matt's rates: 2-in rigid under basement slab 1,241 SF @ $3.50 (moved to Sitework), crushed stone 79.4 CY @ $105 (slabs 70.2 + footings 9.2), dampproofing 1,937 SF @ $2.50 (upper bound), foundation drain 152 LF @ $18. Confirmed: 15-mil vapor barrier 1,365 SF @ $0.85 (Sitework), precast sill at #003 15.83 LF @ $95. Total $22,929.34. Footing/anchor/threshold/finish lines marked INCL in concrete $/CY; waterproofing membrane EXCLUDED and qualified. | E8: 22929.34 | F8: Vapor barrier and precast sill rates confirmed by Matt 2026-09-23. No action.
A9: 4 | B9: HIGH | C9: Markups | D9: Takeoff Summary adds OH 10%%, Profit 10%%, Contingency 5%%, Insurance 2%% additively (27%%) for $2,068,406.24. This workbook has three compounding markups (GC / Fee / Insurance), left blank. Entering 10 / 15 / 2 here compounds to more than the additive number. | E9: 439739.91 | F9: Decide markup structure and enter the three percentages on the Estimate ladder.
A10: 5 | B10: HIGH | C10: Roofing Membrane | D10: Takeoff prices TPO on all four site-built roof areas. Drawings specify EPDM (Carlisle) everywhere. Priced under the EPDM SOW lines. | E10: 25684.3 | F10: Reprice as EPDM or RFI.
A11: 6 | B11: HIGH | C11: Driveway Surface | D11: Takeoff prices 3,359 SF asphalt. SOW carries cobblestone driveway / auto court with Belgian block curb (Belgian block unpriced). Asphalt priced under the cobblestone line. | E11: 19147.95 | F11: Resolve the driveway conflict RFI, then reprice.
A12: 7 | B12: HIGH | C12: Unpriced Base Scope | D12: 222 base SOW lines have no takeoff price (unshaded rows), including the factory module package and set, crane, excavation and fill, dewatering, slab, dampproofing and foundation drain, EIFS, glass guardrails, insulation, HVAC, plumbing and gas distribution, electrical rough and service, Lutron, site utilities, retaining walls and interior stair. | F12: Get sub numbers or carry allowances before issue.
A13: 8 | B13: MED | C13: Steel Units | D13: HSS posts P1-P5, (2) 2x6 steel plates and the W12x65 column are in EA, but the quantities are pounds (about $3.50 per unit). Totals are fine; the unit label is wrong. | E13: 100111.2 | F13: Relabel as LB in the takeoff.
A14: 9 | B14: MED | C14: Steel Duplicate Risk | D14: Three W12x65 lines: unassigned F/I W12x65 1,245.4 LB (row 67), W12x65 Steel Beam 1,964.95 LB and W12x65 Column 1,300. Row 67 has no division and looks like a leftover. Mapped with the WF columns on pile caps. | E14: 3736.2 | F14: Confirm or delete row 67.
A15: 10 | B15: MED | C15: Pocket Door 104A | D15: Takeoff prices F/O door 104A and Johnson soft-close hardware. Drawings say 104A comes factory-supplied, shipped loose. Added as amber lines; likely double count. | E15: 1000 | F15: Confirm with the factory estimate; delete if included.
A16: 11 | B16: MED | C16: Lighting Split | D16: L12A, L12B and L1A are priced F/I, so their I/O rows show INCL. L4 is priced F/O only, so I/O L4 (38 EA) is unpriced. L1/L2, L8, L19, L20 (F/O) and L21 are unpriced. L6A millwork lights are priced but not in the SOW. | F16: Price the missing F/O and I/O lines.
A17: 12 | B17: MED | C17: Framing Area Assignment | D17: The takeoff has unlabeled roof and wall assemblies. My calls: 951 + 151 SF TJI/ZIP roofs go to site-built roof overhangs (1,102.55 SF); 1,042 + 118 SF 2x10/OSB roofs go to the garage roof (1,160.30 SF); the 148.5 SF 2x6/CDX/Tyvek wall goes to the garage exterior wall; the 218 SF 2x4 wall goes to interior partitions. Matching roofing and flashing follow the same split. | E17: 58823.24 | F17: Confirm areas against the takeoff markups.
A18: 13 | B18: MED | C18: Window Install Labor | D18: I/O Window (22 EA, $6,600) spread at $300/EA across basement (3), front stair (16) and garage (3). The I/O French door goes with garage door #128. | E18: 7800 | F18: None if the split is right.
A19: 14 | B19: LOW | C19: Drain Inlets | D19: All six precast inlets (18, 24 and 36 in.) carried on the driveway / north-of-house inlet line. The CULTEC solid-cover inlets show INCL. | E19: 15500 | F19: Split by location if the Owner wants the detail.
A20: 15 | B20: LOW | C20: Temporary Fencing | D20: 963.63 LF temporary construction fence is mapped to project limiting fence. Construction fence around the infiltration areas is unpriced. | E20: 6745.41 | F20: Confirm the takeoff fence covers both.
A21: 16 | B21: LOW | C21: Siding at Garage | D21: One S-1 cedar siding quantity (4,304.92 SF) covers house and garage. The garage siding line shows INCL. | F21: Split if garage is priced separately.
A22: 17 | B22: HIGH | C22: Conflict -- Window / Exterior Door Manufacturer | D22: MARVIN ESSENTIAL / ELEVATE COLLECTION (A0.20 Gen. Notes 01-02) vs. ANDERSEN A-SERIES WINDOW & EXTERIOR DOOR PACKAGE PER QUOTE #9308634 (SBS 5-2) | F22: RFI to Re4a; carry first-listed spec until answered.
A23: 18 | B23: HIGH | C23: Conflict -- HVAC System Type | D23: GEOTHERMAL SMALL-DUCT, HIGH-VELOCITY SYSTEM (SUPP Sec. 6.14; GEO HEAT PUMP / FLOW CENTER / GEO BUFFER on A1.20; TAPROOTGEO on SBS 6-1) vs. WEIL-MCLAIN HIGH-EFFICIENCY "ULTRA" GAS BOILER W/ HYDRO AIR HEATING & HIGH VELOCITY A/C (A0.10) | F23: RFI to Re4a; carry first-listed spec until answered.
A24: 19 | B24: HIGH | C24: Conflict -- Driveway Surface | D24: COBBLESTONE, DETAILS TBD (A0.10, SUPP Sec. 6.2, landscape renderings) vs. PROPOSED ASPHALT DRIVEWAY W/ BELGIAN BLOCK CURB, 2" TOP COURSE TYPE 6 F2 OVER 4" TYPE 2 SUBBASE (C-2, C-4) | F24: RFI to Re4a; carry first-listed spec until answered.
A25: 20 | B25: HIGH | C25: Conflict -- Auto Court Retaining Wall and Stone Landscape Wall | D25: GC SCOPE PER KEYNOTE 2 / SUPP Sec. 6.4 / A0.02 (A1.10-A1.12, SUPP) vs. PROPOSED RETAINING WALL (BY OTHERS) / PROPOSED STONE LANDSCAPE WALL (BY OTHERS) (C-2) | F25: RFI to Re4a; carry first-listed spec until answered.
A26: 21 | B26: MED | C26: Conflict -- Retaining Wall Finish | D26: PARGED POURED-CONCRETE RETAINING WALLS WITH PRECAST CONCRETE COPING (SUPP Sec. 6.4, A2.00 Gen. Note 05) vs. W/ STACKED STONE VENEER AND STONE COPING (S-RL A1.10 Keynote 2) | F26: RFI to Re4a; carry first-listed spec until answered.
A27: 22 | B27: MED | C27: Conflict -- Foundation Wall Exterior Finish | D27: SPEC'D EIFS ASSEMBLY / SPEC'D STUCCO OVER 3" EIFS SYSTEM BY GC (02/A1.10, 02/A3.00) vs. SPEC'D STONE VENEER W/ AIR SPACE OVER SPEC'D CONT. RIGID INSULATION (S-RL A1.10 Detail 02) | F27: RFI to Re4a; carry first-listed spec until answered.
A28: 23 | B28: MED | C28: Conflict -- Under-Slab Barrier | D28: STEGO WRAP 15-MIL VAPOR BARRIER (04/A0.24) vs. OVER VAPOR BARRIER TYP. (02/A1.10) vs. OVER WATER MEMBRANE BARRIER TYP. (S-RL A1.10 Detail 02) | F28: RFI to Re4a; carry first-listed spec until answered.
A29: 24 | B29: MED | C29: Conflict -- P1 Post Size | D29: P1 - HSS 12x4x1/2" (S-RL A1.11-A1.13 legend) vs. P1 - HSS 12x3x3/8" (S-RL A1.10 legend) vs. 4"X12" RECTANGULAR STEEL POSTS (Arch Keynote 1) | F29: RFI to Re4a; carry first-listed spec until answered.
A30: 25 | B30: MED | C30: Conflict -- Garage Roof LVL Beam | D30: (3) 1 3/4"X9 1/2" LVL vs. (3) 1 3/4"x9 1/4" LVL (both on S-RL A1.12) | F30: RFI to Re4a; carry first-listed spec until answered.
A31: 26 | B31: MED | C31: Conflict -- Solar Conduit Type | D31: (2X) 2" PVC CONDUIT (A1.30-A1.33) vs. SOLAR CONDUIT: (2X) 2" EMT BY FACTORY (A0.10) vs. 2" EMT CONDUIT FOR FUTURE SOLAR (SBS 7-33) | F31: RFI to Re4a; carry first-listed spec until answered.
A32: 27 | B32: MED | C32: Conflict -- Slope Erosion Matting | D32: PYRAMAT HIGH PERFORMANCE TURF REINFORCEMENT MAT (HPTRM) BY GEOSOLUTIONS (C-4) vs. CURLEX EXCELSIOR EROSION CONTROL BLANKETS (AMERICAN EXCELSIOR OR APPROVED EQUAL) (Narrative p.14) | F32: RFI to Re4a; carry first-listed spec until answered.
... A77: 72 | B77: LOW | C77: TBD -- Utility Service Routes and Sizes | D77: Not shown on civil drawings (C-2) | F77: Carry allowance or qualify in proposal.

Sheet Quantity Basis
A1: Internal -- quantity basis by line
A3: CSI | B3: Trade | C3: Scope Item | D3: Qty | E3: Unit | F3: Basis
A4: 02.41.16 | B4: Demolition | C4: Remove Existing Dwelling And Dispose Off-Site [EXISTING DWELLING TO BE DEMOLISHED AND DISPOSED OF OFF-SITE (TYP.)] | D4: 3391.41 | E4: SF | F4: Source: C-1, A0.10, SUPP Sec. 7.1 | Pricing section: Alternate #1 | TAKEOFF: 3,391.41 SF -- Demo 2 Story House & Covered Porch Including Foundations = $40,696.92 (row 193)
A5: 02.41.16 | B5: Demolition | C5: Remove Existing Pool, Pool Equipment And Associated Concrete Pads, Spa, Pond, Patios And Porch [Not Specified] | F5: Source: A0.10, C-1 | Pricing section: Alternate #1
A6: 02.41.16 | B6: Demolition | C6: Provide Hazardous Materials Evaluation Of Existing Structures Prior To Demolition, Including Handling And Disposal Of Regulated Materials [Not Specified] | F6: Source: C-3 Site Note 5 | Pricing section: Alternate #1
A7: 02.41.16 | B7: Demolition | C7: Remove Existing Utility Pipe, Structures And Loose Fill Within Building Area And Backfill With Controlled Fill [Not Specified] | F7: Source: GEO p.7 | Pricing section: Alternate #1
A8: 02.41.16 | B8: Demolition | C8: Remove Existing Stone Pillars And Metal Gates From Right-Of-Way [EXIST. STONE PILLARS & METAL GATES SHALL BE REMOVED FROM RIGHT-OF-WAY] | D8: 1 | E8: LS | F8: Source: A0.02, C-1 | Pricing section: Hardscape | TAKEOFF: 5.00 EA -- Remove Stone Pillar = $2,500.00 (row 68); 49.60 LF -- Remove Metal Gates = $744.00 (row 69)
A9: 02.41.16 | B9: Demolition | C9: Remove Existing Stone Retaining Wall Remnant And Feather Out Grading To Match Adjacent Contours [EXIST. STONE RETAINING WALL REMNANT TO BE REMOVED. REFER TO ENG. DWGS.] | D9: 80.26 | E9: LF | F9: Source: A0.02, C-1 | Pricing section: Hardscape | TAKEOFF: 80.26 LF -- Remove Retaining Wall = $1,605.20 (row 195)
A10: 02.41.16 | B10: Demolition | C10: Remove Existing Driveway And Associated Steps [EXISTING DRIVEWAY AND ASSOCIATED STEPS TO BE REMOVED (TYP.)] | D10: 6171.87 | E10: SF | F10: Source: A0.10, C-1, C-5 Phase 1A | Pricing section: Hardscape | TAKEOFF: 647.11 SF -- Remove Concrete Walkway = $2,588.44 (row 194); 5,524.76 SF -- Remove Paver Driveway & Patio = $8,287.14 (row 196)
A11: 02.41.16 | B11: Demolition | C11: Protect Existing Stone Walls To Remain Along North And South Property Lines And Existing Northwest Stone Retaining Wall [Not Specified] | F11: Source: A0.02, C-1 | Pricing section: Site
A12: 02.41.16 | B12: Demolition | C12: Protect And Maintain Existing Catch Basins And Drain Inlets To Remain [EXISTING DRAIN INLET TO REMAIN AND BE MAINTAINED] | F12: Source: A0.02, C-1, C-2 | Pricing section: Site
A13: 02.41.16 | B13: Demolition | C13: Protect Adjoining Public And Private Property From Damage During Demolition And Excavation [Not Specified] | F13: Source: C-1 Gen. Note 12 | Pricing section: Site
A14: 03.30.00 | B14: Concrete | C14: F/I Reinforced Concrete Foundation Walls And Footings At House Basement [REINFORCED CONC. FOUNDATION WALL & FOOTING AS PER STR. ENG. DWGS] | D14: 81.9564 | E14: CY | F14: Source: 02/A1.10, S-RL A1.10, SUPP Sec. 6.3 | Pricing section: Foundation | DRAWING TAKEOFF (E26040_Concrete-Takeoff_v2): Basement walls 10" x 12'-10" 62.76 CY @ $660/CY = $41,420.87 [P1.2]; Pit / areaway walls 6.28 CY @ $750/CY = $4,711.91 [P2.2]; Basement footings 24"x12" 12.91 CY @ $540/CY = $6,974.10 [P10.1]
A15: 03.30.00 | B15: Concrete | C15: F/I Spread Footings Bearing On Virgin Soil Or New Structural Fill [NET DESIGN BEARING PRESSURE 4,000 PSF; MINIMUM FROST DEPTH 42 INCHES] | E15: INCL | F15: Source: GEO Table 2 | Pricing section: Foundation | TAKEOFF: included in priced line 033000-0
A16: 03.30.00 | B16: Concrete | C16: F/I 4" Sealed Reinforced Concrete Basement Slab Over Rigid Insulation And Vapor Barrier On Crushed Stone Base [4" SEALED REINFORCED CONCRETE SLAB PER STRUCT. OVER MIN. 2" THK. RIGID INSUL. & STEGO WRAP 15-MIL VAPOR BARRIER ON CRUSHED STONE BASE PER STRUCT.] | D16: 16.0909 | E16: CY | F16: Source: 04/A0.24, 02/A1.10 | Pricing section: Foundation | DRAWING TAKEOFF (E26040_Concrete-Takeoff_v2): Basement slab 4" 16.09 CY @ $690/CY = $11,102.74 [P7.1]
A17: 03.30.00 | B17: Concrete | C17: Provide Smooth Troweled Finish At Basement Slab [CONC. SLAB W SMOOTH TROWELED FINISH IN PHASE 1.] | E17: INCL | F17: Source: A1.40 | Pricing section: Foundation | TAKEOFF: included in priced line 033000-2
A18: 03.30.00 | B18: Concrete | C18: F/I Crushed Stone Cushion Below Slab [CRUSHED STONE CUSHION THICKNESS 6 INCHES] | D18: 70.18 | E18: CY | F18: Source: GEO Table 4 | Pricing section: Foundation | Matt rate $105/CY. 6-in crushed stone under basement 22.99 + garage 15.22 + terrace 29.92 CY + stair bases 2.05 CY (takeoff P7.3, P8.3, P9.3, P13.4, P14.4).
A19: 03.30.00 | B19: Concrete | C19: F/I Recessed Threshold Formed Into Concrete Foundation Wall And Formed Concrete Ledge At Sliding Door #003 [FORMED CONC. LEDGE PER STRUCT. TO SUPPORT MASONRY SILL ABOVE] | E19: INCL | F19: Source: 04/A0.24 | Pricing section: Foundation | TAKEOFF: included in priced line 033000-0
A20: 03.30.00 | B20: Concrete | C20: F/I Crushed Stone Footing [CRUSHED STONE FOOTING - DEPTH & TYPE TBD BY GC PER LOCAL CODES] | D20: 9.225 | E20: CY | F20: Source: 02/A1.10 | Pricing section: Foundation | Matt rate $105/CY. Stone under basement footings, 3 ft wide x 6 in (takeoff P10.5). Depth 'TBD by GC per local codes': 6 in carried.
A21: 03.30.00 | B21: Concrete | C21: F/I Concrete Pile Caps At Rear Deck [9'x9' PILE CAP W/ (4) PILES] | D21: 18.9 | E21: CY | F21: Source: S-RL A1.10 | Pricing section: Decks | DRAWING TAKEOFF (E26040_Concrete-Takeoff_v2): Pile caps 9'x9' (2) 18.90 CY @ $750/CY = $14,175.00 [P6.1]
A22: 03.30.00 | B22: Concrete | C22: F/I Garage Foundation Walls, Frost Walls And Footings [PER STR. ENG. DWGS] | D22: 32.8928 | E22: CY | F22: Source: 02/A1.10, S-RL A1.10, 01/A3.00 | Pricing section: Garage | DRAWING TAKEOFF (E26040_Concrete-Takeoff_v2): Garage frost walls 10" x 5'-10" 23.35 CY @ $600/CY = $14,008.27 [P3.2]; 77% of Garage + pier footings 24"x12" 9.55 CY @ $540/CY = $5,154.66 [P11.1]
A23: 03.30.00 | B23: Concrete | C23: F/I Garage And Garage Storage Slab On Grade With Smooth Troweled Finish [CONC. SLAB W SMOOTH TROWELED FINISH] | D23: 10.6556 | E23: CY | F23: Source: A1.41, A2.10 | Pricing section: Garage | DRAWING TAKEOFF (E26040_Concrete-Takeoff_v2): Garage slab 4" 10.66 CY @ $630/CY = $6,713.00 [P8.1]
A24: 03.30.00 | B24: Concrete | C24: F/I Terrace Slab On Grade And Concrete Piers / Footings At Outdoor Living, Dining And Kitchen [SLAB ON GRADE] | D24: 31.2072 | E24: CY | F24: Source: S-RL A1.11, 01/A2.10, SUPP Sec. 5 | Pricing section: Foundation | DRAWING TAKEOFF (E26040_Concrete-Takeoff_v2): Terrace slab 4" 20.95 CY @ $630/CY = $13,195.70 [P9.1]; Terrace pier walls (3 x 12') 5.58 CY @ $690/CY = $3,848.18 [P5.2]; 23% of Garage + pier footings 24"x12" 2.82 CY @ $540/CY = $1,521.66 [P11.1]; Isolated post footings (12) 1.87 CY @ $798/CY = $1,489.60 [P16.1]
A25: 03.30.00 | B25: Concrete | C25: Set Anchor Bolts For 2X8 Double Sill Plates On Foundation Walls [ANCHOR BOLTS PER STR. ENG. DWGS] | E25: INCL | F25: Source: A1.10 Gen. Note 01, 02/A1.10 | Pricing section: Foundation | TAKEOFF: included in priced line 033000-0
A26: 03.30.00 | B26: Concrete | C26: F/I Footings And Base Plate Anchorage For Structural Steel Posts [Not Specified] | E26: INCL | F26: Source: S-RL A1.11, S-RL A1.12 | Pricing section: Foundation | TAKEOFF: included in priced line 033000-10
A27: 03.40.00 | B27: Concrete | C27: F/I Precast Concrete Sill Sloped To Drain On Mortar Bed With Weeps At Sliding Door #003 [PRECAST CONC. SILL, SLOPED TO DRAIN] | D27: 15.83 | E27: LF | F27: Source: 02/A0.24, 04/A0.24 | Pricing section: Foundation | Confirmed rate (Matt 2026-09-23): precast sill at sliding door #003, 15'-10" R.O., $95/LF furnished and set on mortar bed.
A28: 05.12.00 | B28: Structural Steel | C28: F/I Structural Steel Beams At First Floor Deck And Module D [W10x26; W12x65; W16x89] | D28: 12552.05 | E28: LB | F28: Source: S-RL A1.11, SUPP Sec. 6.5 | Pricing section: Decks | TAKEOFF: 4,927.04 LB -- F/I W16x89 Steel Beam = $14,781.12 (row 77); 2,240.42 LB -- F/I W10x26 Steel Beam = $6,721.26 (row 78); 1,964.95 LB -- F/I W12x65 Steel Beam = $5,894.85 (row 79); 3,079.96 LB -- F/I W10x26 Steel Beam = $9,239.88 (row 85); 339.68 LB -- F/I W10x22 Steel Beam = $1,019.04 (row 86)
A29: 05.12.00 | B29: Structural Steel | C29: F/I Structural Steel Beams At Module Bearing Lines [W14X38; W14X68] | D29: 5945.88 | E29: LB | F29: Source: S-RL A1.11 | Pricing section: House | TAKEOFF: 4,647.80 LB -- F/I W14x68 Steel Beam = $13,943.40 (row 75); 1,298.08 LB -- F/I W14x38 Steel Beam = $3,894.24 (row 76)
A30: 05.12.00 | B30: Structural Steel | C30: F/I Structural Steel Beams At Second Floor Overhang / Module E And F Support [W10X26; W10X22; W16X67; W16X89] | D30: 12066.03 | E30: LB | F30: Source: S-RL A1.12 | Pricing section: House | TAKEOFF: 12,066.03 LB -- F/I W16x67 Steel Beam = $36,198.09 (row 87)
A31: 05.12.00 | B31: Structural Steel | C31: F/I Steel Tube Beams At Garage Roof Edge [HSS 9x5x1/4"] | D31: 518.13 | E31: LB | F31: Source: S-RL A1.12 | Pricing section: Garage | TAKEOFF: 518.13 LB -- F/I HSS 9x5x1/4" Steel Beam = $1,813.45 (row 89)
A32: 05.12.00 | B32: Structural Steel | C32: Provide Moment Connections Where Indicated [MOMENT CONNECTION] | F32: Source: S-RL A1.11, S-RL A1.12, S-RL A1.13 | Pricing section: House
A33: 05.12.00 | B33: Structural Steel | C33: F/I P1 Structural Posts Supporting Second Floor Modules At Terrace [P1 - HSS 12x4x1/2"] | D33: 13189.5 | E33: EA | F33: Source: S-RL A1.11, A1.11 Keynote 1 | Pricing section: House | TAKEOFF: 13,189.50 EA -- F/I HSS 12x4x1/2" = $46,163.25 (row 84)
A34: 05.12.00 | B34: Structural Steel | C34: F/I P2 Structural Posts Supporting Deck / Overhang [P2 - (2) 2x6 STL. PLATE] | D34: 9792 | E34: EA | F34: Source: S-RL A1.11, A1.10 Keynote 4 | Pricing section: Decks | TAKEOFF: 9,792.00 EA -- F/I (2) 2x6 Steel Plates = $30,355.20 (row 81)
A35: 05.12.00 | B35: Structural Steel | C35: F/I P3 Posts At Front Stair Glazing [P3 - HSS 6x6x1/2"] | D35: 3524 | E35: EA | F35: Source: S-RL A1.11, S-RL A1.12 | Pricing section: House | TAKEOFF: 3,524.00 EA -- F/I HSS 6x6x1/2" = $12,334.00 (row 83)
A36: 05.12.00 | B36: Structural Steel | C36: F/I P4 Posts At Basement And Module Bearing Lines [P4 - HSS 5x5x1/4"] | D36: 1249.6 | E36: EA | F36: Source: S-RL A1.10, S-RL A1.11 | Pricing section: House | TAKEOFF: 1,249.60 EA -- F/I HSS 5x5x1/4" = $4,373.60 (row 82)
A37: 05.12.00 | B37: Structural Steel | C37: F/I P5 Posts At Garage And Garage Storage [P5 - HSS 5x5x1/2"] | D37: 852.9 | E37: EA | F37: Source: S-RL A1.11, S-RL A1.12 | Pricing section: Garage | TAKEOFF: 852.90 EA -- F/I HSS 5x5x1/2" = $2,985.15 (row 80)
A38: 05.12.00 | B38: Structural Steel | C38: F/I Steel WF Columns On Pile Caps At Rear Deck [STEEL WF COLUMN] | D38: 1 | E38: LS | F38: Source: S-RL A1.10, S-RL A1.11 | Pricing section: Decks | TAKEOFF: 1,300.00 EA -- F/I W12X65 Column = $3,900.00 (row 88); 1,245.40 LB -- F/I W12x65 = $3,736.20 (row 67)
A39: 05.12.00 | B39: Structural Steel | C39: F/I Structural Steel Slats / Columns At Terrace Painted Black To Match Infill Panels [SHOP-APPLIED EPOXY PRIMER & ALIPHATIC POLYURETHANE TOP COAT, OR APPR'D EQ APPROPRIATE FOR HIGH-EXPOSURE ENVIRONMENT.] | F39: Source: A0.10 | Pricing section: Hardscape
A40: 05.70.00 | B40: Decorative Metal & Railings | C40: F/I MTL-1 Black Steel Cladding At Center Stair Wall, All Sides [14 GA. HOT-ROLLED BLACK STEEL 5'X10' SHEETS] | F40: Source: A1.11, 01/A2.21, A0.10 | Pricing section: House
A41: 05.70.00 | B41: Decorative Metal & Railings | C41: F/I MTL-1 Black Steel At Stair Floor And Slab Edges [14 GA. HOT-ROLLED BLACK STEEL] | F41: Source: 02/A2.20, 01/A2.21, A0.10 | Pricing section: House
A42: 05.70.00 | B42: Decorative Metal & Railings | C42: F/I MTL-1 Black Steel Wall Cladding At Primary Bedroom 204 [14 GA. HOT-ROLLED BLACK STEEL] | F42: Source: 02/A4.03, 03/A4.03, 06/A4.03, A0.10 | Pricing section: House
A43: 05.70.00 | B43: Decorative Metal & Railings | C43: Clean And Finish MTL-1 Black Steel With Hand-Rubbed Clear Stain And Varnish, Provide Sample For Architect Approval [CLEAN W/DEGREASER & APPLY (2) COATS OLD VILLAGE 1400 CLEAR STAIN & VARNISH (HAND-RUBBED W/CHEESECLOTH OR SIM.)] | F43: Source: A0.10 | Pricing section: House
A44: 05.70.00 | B44: Decorative Metal & Railings | C44: F/I Custom Metal Handrail Brackets Powder-Coated White For Variable Depths At Window Posts And Wall [CUSTOM METAL BRACKETS POWDER-COATED WHITE] | F44: Source: 01/A2.20, SUPP Sec. 6.10 | Pricing section: House
A45: 05.70.00 | B45: Decorative Metal & Railings | C45: F/I Removable Custom Steel Valance At Roller Shades With Recessed Magnets Epoxied Into Head Trim [1/8" THK. STEEL PLATE WELDED TO 1-1/2" X 1-1/2" X 1/8" STEEL ANGLE, POWDER COATED WHITE; 1/2" DIA. X 3/8" THK. NEODYMIUM RARE EARTH DISC MAGNET N42 (PART NO. D86) FROM KJMAGNETICS.COM] | F45: Source: 04/A0.23 | Pricing section: Alternate #13
A46: 05.73.00 | B46: Decorative Metal & Railings | C46: F/I Exterior Glass Guardrails In Concealed Recessed Base Shoe At Decks And Terrace [11/16" LAMINATED, FULLY TEMPERED LOW-IRON GLASS W/ POLISHED FLAT EDGES & FACTORY-APPLIED HYDROPHOBIC COATING IN RECESSED BASE SHOE] | F46: Source: A0.10, A1.10-A1.12 Keynote 3, SUPP Sec. 6.6 | Pricing section: Decks
A47: 05.73.00 | B47: Decorative Metal & Railings | C47: F/I Glass Guardrails At Roof Deck And Roof Access Stair [11/16" LAMINATED, FULLY TEMPERED LOW-IRON GLASS W/ POLISHED FLAT EDGES & FACTORY-APPLIED HYDROPHOBIC COATING IN RECESSED BASE SHOE] | F47: Source: A2.00 Gen. Note 06, SUPP Sec. 8.4, A0.10 | Pricing section: House
A48: 05.73.00 | B48: Decorative Metal & Railings | C48: F/I Stainless Steel Tension Cable Rail System At Interior Stair Window Wall [ABS1SP-19-06 3/16" DIAMETER 316 SS 1X19 CABLE ASSEMBLY THREADED ADJUSTER X SWAGE TOGGLE EYEBOLT CONNECTION; COACH EYE - CS3182-555; CABLE SYSTEM ABS1 THREADED TERMINAL ADJUSTER] | F48: Source: 01/A2.20, 02/A2.20 | Pricing section: House
A49: 05.73.00 | B49: Decorative Metal & Railings | C49: F/I Stainless Steel T-Bar At Stair Treads For Cable Rail Anchorage [3x3x0.25 SS STEEL T BAR] | F49: Source: 01/A2.20, 02/A2.20 | Pricing section: House
A50: 05.73.00 | B50: Decorative Metal & Railings | C50: Provide Deduct Alternate: Replace Glass Guardrails Throughout With Horizontal Stainless-Steel Cable Railing With Minimal Posts And Top Rails [Not Specified] | F50: Source: SUPP Sec. 7.4 | Pricing section: Alternate #4
... A53: 06.10.00 | B53: Rough Carpentry | C53: F/I Framing, Sheathing And Structure At Overhangs And Waterproof Decks [OVERHANGS / WATERPROOF DECKS W/ ASSOCIATED FRAMING, STRUCTURE, ROOFING, AND FINISHES AS PER PLANS] | F53: Source: A0.10 | Pricing section: Decks
A54: 06.10.00 | B54: Rough Carpentry | C54: F/I First Floor Deck Framing And Joists [1 3/4"x9 1/4" LVL @ 16" O.C.; 2x10 LVL @ 16" O.C.] | D54: 1303.72 | E54: SF | F54: Source: S-RL A1.11 | Pricing section: Decks | TAKEOFF: 1,303.72 SF -- F/I 2x10 Deck Framing 1st Floor = $32,593.00 (row 98)
A55: 06.10.00 | B55: Rough Carpentry | C55: F/I Second Floor Deck Framing, Beams, Joists And Ledgers [(3) 1 3/4"x9 1/4" LVL; 2x10 @ 16" O.C.; LEDGER] | D55: 1 | E55: LS | F55: Source: S-RL A1.12 | Pricing section: Decks | TAKEOFF: 1,124.79 SF -- F/I 1-3/4"x9-1/4" LVL Deck Framing = $33,743.70 (row 90); 293.07 LF -- F/O (3) 1-3/4"x9-1/4" LVL = $10,257.45 (row 97)
A56: 06.10.00 | B56: Rough Carpentry | C56: F/I Site-Built Roof Overhang And Roof Deck Perimeter Framing, Beams, Headers And Ledgers [(3) 1 3/4"x 11 7/8" LVL; (3) 1 3/4"x 9 1/4" LVL; 2x10 @ 16" O.C.; (2) 2x10 LEDGER] | D56: 1102.55 | E56: SF | F56: Source: S-RL A1.13, A1.12 | Pricing section: House | TAKEOFF: 713.35 LF -- I-Joist (TJI) TJI 14" @ 16" OC = $4,626.07 (row 91); 19.02 LF -- Ridge Beam = $123.45 (row 92); 951.13 SF -- Zip 7/16" = $2,086.59 (row 93); 113.57 LF -- I-Joist (TJI) TJI 14" @ 16" OC = $736.50 (row 94); 3.03 LF -- Ridge Beam = $19.67 (row 95); 151.42 SF -- Zip 7/16" = $332.19 (row 96)
A57: 06.10.00 | B57: Rough Carpentry | C57: Provide Deck And Terrace Slope Framing [ALL DECK SLOPE BY GC TYP.] | F57: Source: A1.11, A1.12 Plan Notes | Pricing section: Decks
A58: 06.10.00 | B58: Rough Carpentry | C58: F/I Covered Deck And Ramp At Outdoor Living [DECK & RAMP BY G.C.] | F58: Source: 02/A2.00 | Pricing section: Decks
A59: 06.10.00 | B59: Rough Carpentry | C59: F/I Roof Overhang Framing At Garage Door And Outdoor Living [ROOF OVERHANG, BY G.C.] | F59: Source: 02/A2.01, 02/A2.00 | Pricing section: Garage
A60: 06.10.00 | B60: Rough Carpentry | C60: F/I Garage Exterior Wall Framing And Sheathing [1/2" ZIP SHEATHING OVER 2X6 FRAMING BY GC, TYP.] | D60: 148.5 | E60: SF | F60: Source: 01/A3.00, A0.10 | Pricing section: Garage | TAKEOFF: 17.00 EA -- 2x6x9' Studs = $295.73 (row 99); 33.00 LF -- 2x6 Top Plates = $64.09 (row 100); 16.50 LF -- 2x6 Bottom Plates = $32.05 (row 101); 4.00 EA -- 5/8" CDX Plywood Sheathing (4x10) = $211.97 (row 102); 148.50 SF -- Tyvek HomeWrap = $84.79 (row 125)
A61: 06.10.00 | B61: Rough Carpentry | C61: F/I Garage Roof Framing, Beams And Ledger [14" TJI 360 @ 16" O.C.; (3) 1 3/4"X9 1/2" LVL] | D61: 1160.3 | E61: SF | F61: Source: 01/A3.00, S-RL A1.12 | Pricing section: Garage | TAKEOFF: 781.46 LF -- 2x10 @ 16" OC = $3,854.94 (row 103); 20.84 LF -- Ridge Board / Beam = $135.26 (row 104); 1,041.95 SF -- 7/16" OSB = $2,285.83 (row 105); 88.76 LF -- 2x10 @ 16" OC = $437.85 (row 106); 2.37 LF -- Ridge Board / Beam = $15.38 (row 107); 44.38 LF -- Every Other = $141.99 (row 108); 118.35 SF -- 7/16" OSB = $259.64 (row 109)
A62: 06.10.00 | B62: Rough Carpentry | C62: I/O Factory-Panelized Parapet Walls / Curbs Shipped Loose And Provide Connections With Ply Panel [2X6 FRAMING, 1/2" EXT GRADE PLY. SHEATHING INSIDE AND OUTSIDE (PANELIZED & SHIPPED LOOSE BY FACTORY, ON-SITE INSTALLATION & CONNECTIONS BY GC)] | F62: Source: A0.10, A1.10-A1.13 Keynote 7, 02/A3.00, A5.01 Gen. Note 01 | Pricing section: House
A63: 06.10.00 | B63: Rough Carpentry | C63: F/I Roof Parapets Not Over Modules [Not Specified] | F63: Source: A2.00 Keynote 11 | Pricing section: House
A64: 06.10.00 | B64: Rough Carpentry | C64: F/I Wood Framing For Hung Ceilings And Exterior Sheathing At Stucco Ceilings [Not Specified] | F64: Source: A2.00 Keynote 9 | Pricing section: House
A65: 06.10.00 | B65: Rough Carpentry | C65: F/I 5/8" Plywood Roof Sheathing At Site-Built Roofs [EXTERIOR SHEATHING: 5/8" PLYWOOD] | F65: Source: A0.10 | Pricing section: House
A66: 06.10.00 | B66: Rough Carpentry | C66: F/I ZIP System Wall Sheathing And Tape At Site-Built Exterior Walls [1/2" ZIP SYSTEM WALL & TAPE] | F66: Source: A0.10, A2.10 | Pricing section: House
A67: 06.10.00 | B67: Rough Carpentry | C67: F/I Interior Partition Framing Outside Modules [2X4 WOOD STUDS @ 16" O.C., U.O.N.] | D67: 218.34 | E67: SF | F67: Source: A0.10 | Pricing section: House | TAKEOFF: 13.00 EA -- 2x4x9' Studs = $158.11 (row 114); 24.26 LF -- 2x4 Top Plates = $47.12 (row 115); 12.13 LF -- 2x4 Bottom Plates = $23.56 (row 116)
A68: 06.10.00 | B68: Rough Carpentry | C68: F/I 2X Stud Framing At Basement Walls To Receive Wall-Mounted Equipment [WALLS TO RECEIVE WALL-MTD EQUIP TO BE FRAMED OUT W/ 2X STUDS AS INDICATED IN PHASE I.] | F68: Source: A1.10 | Pricing section: House
A69: 06.10.00 | B69: Rough Carpentry | C69: F/I Temporary Basement Walls [TEMPORARY WALLS & DOOR IN PHASE 1 (AS HATCHED) - CONFIGURATION TBC] | F69: Source: A1.10, SUPP Sec. 2 | Pricing section: House
A70: 06.10.00 | B70: Rough Carpentry | C70: F/I Pressure Treated Wood Bucks And Plywood Pad-Out At Basement Openings #001, #002, #003 [2X6 P.T. WOOD BUCK, TYP.] | F70: Source: 01/A0.24, 02/A0.24, 03/A0.24 | Pricing section: House
A71: 06.10.00 | B71: Rough Carpentry | C71: F/I Blocking / Framing At Window Heads For Anchoring Tension Cable Rail [BLOCKING / FRAMING AS REQ'D. AT WINDOW HEAD FOR ANCHORING TENSION CABLE RAIL] | F71: Source: 01/A2.20 | Pricing section: House
A72: 06.10.00 | B72: Rough Carpentry | C72: F/I Blocking For 1-3/4" Trim Projection Where Window Trim Is Grouped With Adjacent Door Unit [Not Specified] | F72: Source: 03/A0.21 | Pricing section: House
A73: 06.10.00 | B73: Rough Carpentry | C73: F/I Blocking For Wall-Mounted TV Locations Outside Modules [Not Specified] | F73: Source: A1.30 Elec. Note 09 | Pricing section: House
A74: 06.15.00 | B74: Decking | C74: F/I FL-2 Ipe Decking At First And Second Floor Decks With Concealed Fasteners [IPE, PRE-GROOVED 5/4 X 6 W/ CONCEALED FASTENERS (TIGERCLAW OR SIM.)] | D74: 2405.66 | E74: SF | F74: Source: A0.10 Finish Sch., A1.41, A1.42 | Pricing section: Decks | TAKEOFF: 927.93 SF -- F/I Decking First Floor [IPE, Pre-Grooved] = $37,117.20 (row 110); 1,477.73 SF -- F/I Decking Second Floor [IPE, Pre-Grooved] = $59,109.20 (row 111)
A75: 06.15.00 | B75: Decking | C75: F/I Deck Pedestals / Sleepers Over EPDM At Decks Over Roofing [Not Specified] | F75: Source: 10/A5.00 | Pricing section: Decks
A76: 06.15.00 | B76: Decking | C76: Provide Samples Of Decking For Owner / Architect Approval [Not Specified] | F76: Source: A0.10 Finish Sch. | Pricing section: Decks
A77: 06.15.00 | B77: Decking | C77: F/I Ipe Cladding At Roof Access Stair [FINISHED IPE-CLAD STAIR] | F77: Source: SUPP Sec. 8.4 | Pricing section: House
A78: 06.15.00 | B78: Decking | C78: F/I Ipe Decking On Sleepers Over EPDM Roof At Upper Roof Deck [Not Specified] | F78: Source: SUPP Sec. 7.5, 09/A5.00 | Pricing section: Alternate #5
A79: 06.20.00 | B79: Finish Carpentry & Stairs | C79: F/I S-2 Light Cedar Ceilings Over Factory OSB At Living / Dining, Kitchen Cove And Primary Bedroom [WESTERN RED CEDAR, GRADE A CLEAR OR BETTER 1X6 T&G] | F79: Source: A1.21, A1.22, A0.10 | Pricing section: House
A80: 06.20.00 | B80: Finish Carpentry & Stairs | C80: F/I Interior Window Trim At All Windows Except Bathroom Corian Trim [KILN-DRIED AND PLANED POPLAR] | F80: Source: A0.20 Gen. Note 12 | Pricing section: House
A81: 06.20.00 | B81: Finish Carpentry & Stairs | C81: F/I Knife Edge Casing Detail At Exterior Doors And Windows [Not Specified] | F81: Source: SBS 8-14, 03/A0.21 | Pricing section: House
A82: 06.20.00 | B82: Finish Carpentry & Stairs | C82: I/O Factory-Supplied Base Molding In Modules (Tacked By Factory) And F/I Base Molding Outside Modules [3 1/2" X 1/2" SQUARE WOOD TRIM, FACTORY PRIMED, MITERED CORNERS] | F82: Source: A0.10 | Pricing section: House
A83: 06.20.00 | B83: Finish Carpentry & Stairs | C83: Fill And Sand Joints At Factory-Installed Door Trim Prior To Painting And F/I All Trim Outside Modules [Not Specified] | F83: Source: A0.10 | Pricing section: House
A84: 06.20.00 | B84: Finish Carpentry & Stairs | C84: Complete Door Trim At Mate Lines And Guest Bed 104 Side Left Off By Factory [Not Specified] | F84: Source: A0.30 Door 104A, 105A | Pricing section: House
A85: 06.20.00 | B85: Finish Carpentry & Stairs | C85: F/I Cedar Top Rail On Cedar Posts At Parapet Railing [2X12 CEDAR TOP RAIL ATTACHED TO CEDAR POSTS WITH (2) #12 X 6" S.S. SCREWS @ EACH POST] | F85: Source: 09/A5.00 | Pricing section: House
A86: 06.20.00 | B86: Finish Carpentry & Stairs | C86: F/I Cedar Slat Screens / Slat Wall At Decks Stained To Match Siding [CEDAR SLAT WALL PER CONSTR. PLAN STAINED TO MATCH SIDING - BY GC.] | F86: Source: A0.10, A2.00 Keynote 5 | Pricing section: Decks
... A102: 06.40.00 | B102: Custom Millwork & Closets | C102: Provide Coordination Of Closet Factory Shop Drawings [Not Specified] | F102: Source: A0.10 Finish Sch. | Pricing section: House
A103: 07.10.00 | B103: Waterproofing & Foundation Drainage | C103: F/I Dampproofing On Outside Face Of Below-Grade Foundation Walls [DAMP-PROOFING ON CONC. FOUNDATION WALL AS REQ'D] | D103: 1936.56 | E103: SF | F103: Source: GEO p.11, 01/A0.24 | Pricing section: Foundation | Matt rate $2.50/SF. Full height of basement walls (takeoff X.1): upper bound, walkout faces partly exposed.
A104: 07.10.00 | B104: Waterproofing & Foundation Drainage | C104: F/I Waterproofing Membrane And Drainage Mat At Foundation Walls As Required [WATERPROOFING MEMBRANE & DRAINAGE MAT AS REQ'D.] | E104: EXCL | F104: Source: 02/A1.10, 02/A3.00 | Pricing section: Foundation
A105: 33.46.00 | B105: Waterproofing & Foundation Drainage | C105: F/I Perforated PVC Foundation Drain In Crushed Stone Wrapped In Geotextile, Discharge To Daylight Or Storm System [MINIMUM 4-INCH DIAMETER RIGID WALL PERFORATED PVC PIPE SURROUNDED BY AT LEAST 12 INCHES OF 3/4-INCH CLEAN CRUSHED STONE WRAPPED IN GEOTEXTILE (MIRAFI 140N OR EQUIVALENT)] | D105: 152.3 | E105: LF | F105: Source: 02/A1.10, GEO p.11 | Pricing section: Foundation | Matt rate $18/LF. Basement outside-face perimeter from dim strings (takeoff X.2).
A106: 07.21.00 | B106: Insulation | C106: F/I Continuous Exterior Insulation At Walls [ROCKWOOL 1.25 COMFORTBOARD. (CONTINUOUS R-5.25).] | F106: Source: A0.10 | Pricing section: House
A107: 07.21.00 | B107: Insulation | C107: F/I Cavity Insulation At All Exterior Walls Outside Modules [HIGH-DENSITY FIBERGLASS BATT INSUL (CAVITY R-21)] | F107: Source: A0.10 | Pricing section: House
A108: 07.21.00 | B108: Insulation | C108: F/I Insulation At First Floor Modules Over Basement [R-30 FIBERGLASS W/ VAPOR BARRIER, TYP.] | F108: Source: A0.10, 02/A1.10 | Pricing section: House
A109: 07.21.00 | B109: Insulation | C109: F/I Closed-Cell Spray Foam Insulation Where Floor Underside Exposed [12" CLOSED-CELL SPRAY FOAM INSULATION (R-84 TOTAL)] | F109: Source: A0.10 | Pricing section: House
A110: 07.21.00 | B110: Insulation | C110: F/I Spray Foam Insulation At Gaps At Exterior Walls, Windows And Between Modules After Set [Not Specified] | F110: Source: A1.11 Gen. Note 07, SUPP Sec. 4 | Pricing section: House
A111: 07.21.00 | B111: Insulation | C111: F/I Sound Attenuation Insulation At Partitions Outside Modules [R-13 SOUND ATTENUATION] | F111: Source: A0.10 | Pricing section: House
A112: 07.21.00 | B112: Insulation | C112: F/I Framing, Sheathing And Insulation At Stair Volume Roof [FLASH & BATT: 2" FOMO SPRAY FOAM INSUL. + R-21 FIBERGLASS BATT INSUL. (R-49 TOTAL MINIMUM- INCLUDES CONT. TAPERED RIGID INSULATION.)] | F112: Source: A0.10 | Pricing section: House
A113: 07.21.00 | B113: Insulation | C113: F/I Flash And Batt Insulation In Garage Roof Cavity [FLASH & BATT INSULATION IN ROOF CAVITY AS SPEC'D] | F113: Source: 01/A3.00 | Pricing section: Garage
A114: 07.21.00 | B114: Insulation | C114: F/I Closed-Cell Spray Foam Insulation At North First Floor Deck Over Basement [CLOSED-CELL SPRAY FOAM INSULATION UP TO R-70, PENDING RESCHECK/ENERGY CALCULATIONS] | F114: Source: SUPP Sec. 6.12 | Pricing section: Decks
A115: 07.21.00 | B115: Insulation | C115: F/I Rigid Insulation Under Basement Slab [2" THK RIGID INSUL. (R-10)] | D115: 1241.3 | E115: SF | F115: Source: 02/A1.10 | Pricing section: Foundation | Matt rate $3.50/SF. 2-in rigid R-10 under basement slab = basement slab area 1,241.3 SF (takeoff P7.6). Carried in SITEWORK per Matt.
A116: 07.24.00 | B116: EIFS & Stucco | C116: F/I S-3 EIFS At Exposed Concrete Foundation Walls [1/4" THICK BASE + FINISH COATS W/ EMBEDDED FIBERGLASS REINFORCING MESH OVER 3" THK. CONT. INSUL. & 1/4" DRAINAGE PLANE BEHIND] | F116: Source: A0.10 Finish Sch. S-3, 02/A1.10, 02/A3.00, A0.24 | Pricing section: Foundation
A117: 09.24.00 | B117: EIFS & Stucco | C117: F/I S-5 Exterior Stucco Ceilings At Terrace, Deck And Soffit Undersides [7/8" THICK PAREX 3-COAT STUCCO ASSEMBLY W/ ELASTOMERIC FINISH; FINISH COLOR: "SNOWBALL" 10400L (75); FINISH TEXTURE: "SAND FINE"] | D117: 4175.27 | E117: SF | F117: Source: A0.10 Finish Sch. S-5, A2.00 Keynote 9, A1.20-A1.22 | Pricing section: House | TAKEOFF: 4,175.27 SF -- F/I Ceiling Stucco S-5 [7/8" THICK PAREX 3-COAT STUCCO- ELASTOMERIC FINISH- "SNOWBALL" 10400L - FINISH TEXTURE: "SAND FINE"] = $75,154.86 (row 74)
A118: 09.24.00 | B118: EIFS & Stucco | C118: Provide Samples Of Stucco Finish For Architect Approval [Not Specified] | F118: Source: A0.10 Finish Sch. | Pricing section: House
...
